{"type":"Topology","transform":{"scale":[0.00000358520420920419,0.000004796188906188976],"translate":[-88.47322184299986,30.211837347000085]},"objects":{"counties":{"type":"GeometryCollection","geometries":[{"type":"Polygon","arcs":[[0,1,2,3]],"id":1077,"properties":{"STATE":"AL","COUNTY":"Lauderdale County","FIPS":"01077"}},{"type":"Polygon","arcs":[[4,5,6,-4,7]],"id":1083,"properties":{"STATE":"AL","COUNTY":"Limestone County","FIPS":"01083"}},{"type":"Polygon","arcs":[[8,9,10,-5,11]],"id":1089,"properties":{"STATE":"AL","COUNTY":"Madison County","FIPS":"01089"}},{"type":"Polygon","arcs":[[12,13,-9,14]],"id":1071,"properties":{"STATE":"AL","COUNTY":"Jackson County","FIPS":"01071"}},{"type":"Polygon","arcs":[[15,16,17,-2]],"id":1033,"properties":{"STATE":"AL","COUNTY":"Colbert County","FIPS":"01033"}},{"type":"Polygon","arcs":[[18,19,20,-13,21]],"id":1049,"properties":{"STATE":"AL","COUNTY":"DeKalb County","FIPS":"01049"}},{"type":"Polygon","arcs":[[-7,22,23,24,25,-16,-1]],"id":1079,"properties":{"STATE":"AL","COUNTY":"Lawrence County","FIPS":"01079"}},{"type":"Polygon","arcs":[[-11,26,27,-23,-6]],"id":1103,"properties":{"STATE":"AL","COUNTY":"Morgan County","FIPS":"01103"}},{"type":"Polygon","arcs":[[-21,28,29,30,-27,-10,-14]],"id":1095,"properties":{"STATE":"AL","COUNTY":"Marshall County","FIPS":"01095"}},{"type":"Polygon","arcs":[[-26,31,32,33,-17]],"id":1059,"properties":{"STATE":"AL","COUNTY":"Franklin County","FIPS":"01059"}},{"type":"Polygon","arcs":[[34,35,36,-19,37]],"id":1019,"properties":{"STATE":"AL","COUNTY":"Cherokee County","FIPS":"01019"}},{"type":"Polygon","arcs":[[38,39,40,41,42,-33]],"id":1093,"properties":{"STATE":"AL","COUNTY":"Marion County","FIPS":"01093"}},{"type":"Polygon","arcs":[[-31,43,44,45,-24,-28]],"id":1043,"properties":{"STATE":"AL","COUNTY":"Cullman County","FIPS":"01043"}},{"type":"Polygon","arcs":[[-25,-46,46,-39,-32]],"id":1133,"properties":{"STATE":"AL","COUNTY":"Winston County","FIPS":"01133"}},{"type":"Polygon","arcs":[[-30,47,48,49,50,-44]],"id":1009,"properties":{"STATE":"AL","COUNTY":"Blount County","FIPS":"01009"}},{"type":"Polygon","arcs":[[-37,51,52,-48,-29,-20]],"id":1055,"properties":{"STATE":"AL","COUNTY":"Etowah County","FIPS":"01055"}},{"type":"Polygon","arcs":[[53,54,55,-42]],"id":1075,"properties":{"STATE":"AL","COUNTY":"Lamar County","FIPS":"01075"}},{"type":"Polygon","arcs":[[-45,-51,56,57,58,-40,-47]],"id":1127,"properties":{"STATE":"AL","COUNTY":"Walker County","FIPS":"01127"}},{"type":"Polygon","arcs":[[59,60,61,62,-49,-53]],"id":1115,"properties":{"STATE":"AL","COUNTY":"Saint Clair County","FIPS":"01115"}},{"type":"Polygon","arcs":[[63,-60,-52,-36,64]],"id":1015,"properties":{"STATE":"AL","COUNTY":"Calhoun County","FIPS":"01015"}},{"type":"Polygon","arcs":[[65,66,67,68,-65,-35]],"id":1029,"properties":{"STATE":"AL","COUNTY":"Cleburne County","FIPS":"01029"}},{"type":"Polygon","arcs":[[-59,69,70,-54,-41]],"id":1057,"properties":{"STATE":"AL","COUNTY":"Fayette County","FIPS":"01057"}},{"type":"Polygon","arcs":[[-63,71,72,73,-57,-50]],"id":1073,"properties":{"STATE":"AL","COUNTY":"Jefferson County","FIPS":"01073"}},{"type":"Polygon","arcs":[[-64,-69,74,75,76,-61]],"id":1121,"properties":{"STATE":"AL","COUNTY":"Talladega County","FIPS":"01121"}},{"type":"Polygon","arcs":[[-58,-74,77,78,79,80,-70]],"id":1125,"properties":{"STATE":"AL","COUNTY":"Tuscaloosa County","FIPS":"01125"}},{"type":"Polygon","arcs":[[-77,81,82,83,-72,-62]],"id":1117,"properties":{"STATE":"AL","COUNTY":"Shelby County","FIPS":"01117"}},{"type":"Polygon","arcs":[[-71,-81,84,85,86,-55]],"id":1107,"properties":{"STATE":"AL","COUNTY":"Pickens County","FIPS":"01107"}},{"type":"Polygon","arcs":[[87,88,89,90,-67]],"id":1111,"properties":{"STATE":"AL","COUNTY":"Randolph County","FIPS":"01111"}},{"type":"Polygon","arcs":[[-91,91,92,-75,-68]],"id":1027,"properties":{"STATE":"AL","COUNTY":"Clay County","FIPS":"01027"}},{"type":"Polygon","arcs":[[93,94,95,-78,-73,-84]],"id":1007,"properties":{"STATE":"AL","COUNTY":"Bibb County","FIPS":"01007"}},{"type":"Polygon","arcs":[[96,97,98,-85,-80]],"id":1063,"properties":{"STATE":"AL","COUNTY":"Greene County","FIPS":"01063"}},{"type":"Polygon","arcs":[[99,100,101,-89]],"id":1017,"properties":{"STATE":"AL","COUNTY":"Chambers County","FIPS":"01017"}},{"type":"Polygon","arcs":[[-102,102,103,104,105,-92,-90]],"id":1123,"properties":{"STATE":"AL","COUNTY":"Tallapoosa County","FIPS":"01123"}},{"type":"Polygon","arcs":[[-106,106,107,-82,-76,-93]],"id":1037,"properties":{"STATE":"AL","COUNTY":"Coosa County","FIPS":"01037"}},{"type":"Polygon","arcs":[[-108,108,109,110,111,-94,-83]],"id":1021,"properties":{"STATE":"AL","COUNTY":"Chilton County","FIPS":"01021"}},{"type":"Polygon","arcs":[[-96,112,113,-97,-79]],"id":1065,"properties":{"STATE":"AL","COUNTY":"Hale County","FIPS":"01065"}},{"type":"Polygon","arcs":[[114,115,116,-86,-99]],"id":1119,"properties":{"STATE":"AL","COUNTY":"Sumter County","FIPS":"01119"}},{"type":"Polygon","arcs":[[-112,117,118,-113,-95]],"id":1105,"properties":{"STATE":"AL","COUNTY":"Perry County","FIPS":"01105"}},{"type":"Polygon","arcs":[[119,120,121,-109,-107,-105]],"id":1051,"properties":{"STATE":"AL","COUNTY":"Elmore County","FIPS":"01051"}},{"type":"Polygon","arcs":[[122,123,124,-103,-101]],"id":1081,"properties":{"STATE":"AL","COUNTY":"Lee County","FIPS":"01081"}},{"type":"Polygon","arcs":[[125,126,127,128,-118,-111]],"id":1047,"properties":{"STATE":"AL","COUNTY":"Dallas County","FIPS":"01047"}},{"type":"Polygon","arcs":[[-122,129,130,-126,-110]],"id":1001,"properties":{"STATE":"AL","COUNTY":"Autauga County","FIPS":"01001"}},{"type":"Polygon","arcs":[[131,132,133,-120,-104,-125]],"id":1087,"properties":{"STATE":"AL","COUNTY":"Macon County","FIPS":"01087"}},{"type":"Polygon","arcs":[[-114,-119,-129,134,135,136,-115,-98]],"id":1091,"properties":{"STATE":"AL","COUNTY":"Marengo County","FIPS":"01091"}},{"type":"Polygon","arcs":[[137,138,139,-132,-124]],"id":1113,"properties":{"STATE":"AL","COUNTY":"Russell County","FIPS":"01113"}},{"type":"Polygon","arcs":[[-134,140,141,142,143,-130,-121]],"id":1101,"properties":{"STATE":"AL","COUNTY":"Montgomery County","FIPS":"01101"}},{"type":"Polygon","arcs":[[-144,144,145,146,-127,-131]],"id":1085,"properties":{"STATE":"AL","COUNTY":"Lowndes County","FIPS":"01085"}},{"type":"Polygon","arcs":[[147,148,149,-116,-137]],"id":1023,"properties":{"STATE":"AL","COUNTY":"Choctaw County","FIPS":"01023"}},{"type":"Polygon","arcs":[[-140,150,151,-141,-133]],"id":1011,"properties":{"STATE":"AL","COUNTY":"Bullock County","FIPS":"01011"}},{"type":"Polygon","arcs":[[-128,-147,152,153,154,-135]],"id":1131,"properties":{"STATE":"AL","COUNTY":"Wilcox County","FIPS":"01131"}},{"type":"Polygon","arcs":[[155,156,157,158,-151,-139]],"id":1005,"properties":{"STATE":"AL","COUNTY":"Barbour County","FIPS":"01005"}},{"type":"Polygon","arcs":[[-159,159,160,161,-142,-152]],"id":1109,"properties":{"STATE":"AL","COUNTY":"Pike County","FIPS":"01109"}},{"type":"Polygon","arcs":[[-162,162,163,164,-145,-143]],"id":1041,"properties":{"STATE":"AL","COUNTY":"Crenshaw County","FIPS":"01041"}},{"type":"Polygon","arcs":[[-155,165,166,167,-148,-136]],"id":1025,"properties":{"STATE":"AL","COUNTY":"Clarke County","FIPS":"01025"}},{"type":"Polygon","arcs":[[-165,168,169,170,-153,-146]],"id":1013,"properties":{"STATE":"AL","COUNTY":"Butler County","FIPS":"01013"}},{"type":"Polygon","arcs":[[-171,171,172,173,-166,-154]],"id":1099,"properties":{"STATE":"AL","COUNTY":"Monroe County","FIPS":"01099"}},{"type":"Polygon","arcs":[[174,175,176,-157]],"id":1067,"properties":{"STATE":"AL","COUNTY":"Henry County","FIPS":"01067"}},{"type":"Polygon","arcs":[[177,178,-172,-170]],"id":1035,"properties":{"STATE":"AL","COUNTY":"Conecuh County","FIPS":"01035"}},{"type":"Polygon","arcs":[[-168,179,180,181,-149]],"id":1129,"properties":{"STATE":"AL","COUNTY":"Washington County","FIPS":"01129"}},{"type":"Polygon","arcs":[[-177,182,183,184,-160,-158]],"id":1045,"properties":{"STATE":"AL","COUNTY":"Dale County","FIPS":"01045"}},{"type":"Polygon","arcs":[[185,186,-163,-161,-185]],"id":1031,"properties":{"STATE":"AL","COUNTY":"Coffee County","FIPS":"01031"}},{"type":"Polygon","arcs":[[-187,187,188,189,-178,-169,-164]],"id":1039,"properties":{"STATE":"AL","COUNTY":"Covington County","FIPS":"01039"}},{"type":"MultiPolygon","arcs":[[[190]],[[191]],[[192]],[[193]],[[-174,194,195,196,197,198,-180,-167]]],"id":1003,"properties":{"STATE":"AL","COUNTY":"Baldwin County","FIPS":"01003"}},{"type":"Polygon","arcs":[[199,200,-183,-176]],"id":1069,"properties":{"STATE":"AL","COUNTY":"Houston County","FIPS":"01069"}},{"type":"Polygon","arcs":[[-190,201,-195,-173,-179]],"id":1053,"properties":{"STATE":"AL","COUNTY":"Escambia County","FIPS":"01053"}},{"type":"Polygon","arcs":[[202,-188,-186,-184,-201]],"id":1061,"properties":{"STATE":"AL","COUNTY":"Geneva County","FIPS":"01061"}},{"type":"MultiPolygon","arcs":[[[203]],[[204]],[[205]],[[206]],[[207]],[[208]],[[-197,209]],[[210,-181,-199]]],"id":1097,"properties":{"STATE":"AL","COUNTY":"Mobile County","FIPS":"01097"}}]},"states":{"type":"GeometryCollection","geometries":[{"type":"MultiPolygon","arcs":[[[203]],[[204]],[[190]],[[191]],[[205]],[[206]],[[207]],[[208]],[[192]],[[193]],[[11,14,21,37,65,87,99,122,137,155,174,199,202,188,201,195,209,197,210,181,149,116,86,55,42,33,17,2,7]]],"properties":{"STATE":"Alabama"}}]}},"arcs":[[[338209,947998],[-2034,95],[-1335,-263],[-1816,-994],[-2637,-302],[-2769,352],[-1843,664],[-2489,1906],[-2998,1909],[-728,994],[-945,2019],[-1173,1440],[-917,669],[-1595,172],[-1469,-536],[-1557,-196],[-2190,206],[-4477,1685],[-1877,98],[-3020,-1631],[-3031,167],[-2116,-221],[-2342,129],[-896,269]],[[291955,956629],[-2869,864],[-4238,766],[-1776,826],[-2058,169],[-3798,-17],[-2468,568],[-2232,922],[-2805,413],[-1445,938],[-690,779],[-1574,386],[-1742,123],[-5691,-282],[-1450,-735],[-1265,-281],[-2884,-226],[-4123,-648],[-1717,-664],[-151,-1031],[-887,-1033],[-1362,-726],[-6392,-1069],[-1728,-897],[-3690,-469],[-876,6],[-3633,-1273],[-3852,-1028],[-1768,-74],[-5689,-1270],[-2368,-379],[-3294,-1341],[-168,-524],[-2482,-2142],[-869,-1218],[-1787,-858],[-1554,138],[-3442,-1109],[-2750,-1118],[-967,-623],[-1349,-377],[-5293,165],[-2228,259],[-2373,-101],[-3153,586],[-903,468],[-4220,894],[-2966,1251],[-3574,2851],[-2443,1362],[-4718,2294],[-3969,2367],[-4567,2061],[-1636,1207],[-1736,2138],[-722,1440],[-922,3330],[-742,1301],[-1147,1405],[-2681,2674],[-2306,1655],[-1414,558],[-2896,1557],[-1185,96],[-2984,896],[-1783,280],[-4928,1435],[-5313,1816],[-2676,493],[-2768,-90],[-2120,-382],[-1482,-475],[-2438,-1112],[-1850,-483],[-1536,-110],[-3625,163],[-85,-516]],[[104690,975848],[-1513,564],[-6799,1742],[-3875,1606],[-3464,2250],[-2606,3295],[-3559,5205],[-2235,1762],[-3461,3529],[-978,1614],[-816,2584],[35535,-296],[25283,-141],[68794,-329],[32744,-163],[74342,-389],[36343,-487],[3708,-72]],[[352133,998122],[-137,-6542],[40,-1195],[-185,-5969],[-44,-5455],[-625,-10496],[-191,-4789],[-17,-3713],[-2255,-1512],[-1910,-777],[-2359,-1269],[-4907,-2240],[-4236,-912],[-1750,-960],[481,-1508],[2642,-1305],[411,-1025],[1118,-457]],[[471264,996647],[-14,-12219],[-134,-8109],[59,-2019],[-269,-10175],[-187,-8891],[-201,-13429],[-94,-9760],[-234,-10096],[-321,-7102],[-392,-10183]],[[469477,904664],[-4533,636],[-3249,192],[-2587,-16],[-2818,278],[-2163,633],[-3246,1372],[-3191,833],[-3417,594],[-3064,768],[-4904,820],[-1773,470],[-2084,852],[-985,198],[-1089,708],[-2163,633],[-1163,825],[-2377,756],[-4117,1729],[-2293,693],[-4395,2518],[-2945,1249],[-1790,544],[-2306,956],[-3333,1987],[-2426,884],[-1770,-33],[-2278,-412],[-4316,2028],[-5878,2152],[-2199,1362],[-691,681],[-2323,1309]],[[381611,932863],[-4590,2536],[-2400,2173],[-692,1708],[-1742,1521],[-3924,1831],[-3641,1312],[-1564,767],[-4125,1254],[-2695,160],[-2408,612],[-2237,1417],[-4424,727],[-3942,249],[-1965,-143],[-2470,-424],[-583,-565]],[[352133,998122],[67129,-938],[37523,-543],[14479,6]],[[603355,996470],[248,-2265],[-1065,-916],[1704,-115],[473,-677],[1137,-81],[390,-540],[1268,-398],[1620,305],[638,-2166],[2027,-1036],[1782,-84],[1685,-1219],[2179,-323],[694,-1718],[-567,-213],[840,-1298],[-133,-600],[-2619,-976],[-1952,482],[-213,923],[-1650,989],[-131,1051],[-2354,141],[-536,870],[-1545,206],[-2346,-947],[-1954,-1127],[-1206,633],[-478,-450],[-2445,289],[1068,-1780],[13,-571],[1667,-598],[1417,-1702],[-1946,-2474],[-1254,-358],[-1854,41],[-665,-618],[-1928,-789],[-803,24],[670,-1218],[-1127,-1908],[-972,-770],[-929,-185],[-156,-487],[1512,-1096],[-489,-1963],[573,-675],[915,-27],[1376,-812],[649,-1061],[-532,-1496],[-553,-464],[3278,-1288],[-2403,-1475],[-367,-998],[-1743,-221],[-596,-996],[125,-1270],[-457,-367],[1283,-856],[-131,-718],[567,-600],[985,74],[636,-1392],[-1154,-134],[-1011,-1542],[-46,-1699],[1085,-1739],[12,-947],[-472,-1187],[-881,-650],[26,-1280],[-712,-95],[-3568,-1763],[-256,-21355],[3104,-1569],[6130,-3235],[-1328,-292],[-271,-693],[1276,-1067]],[[598609,914869],[508,-279],[2580,265],[1244,-783],[1687,-336],[668,-444],[-672,-568],[-449,-1007],[231,-531],[1182,-4],[579,-555],[-820,15],[-2773,-547],[-1955,-215],[-2009,-774],[-849,245],[-463,-564],[840,-1132],[1923,-19],[2758,-479],[687,228],[687,-792],[-1345,-1380],[-319,-1150],[516,-1686],[-3576,-2120],[-935,-1198],[-828,-1811],[70,-543],[-1275,-697],[-826,72],[-1821,1204],[-2792,1314],[-2378,-597],[-625,-750],[-1113,-340],[-2322,1042],[-1923,434],[-508,-658],[-764,-20],[-579,540],[-472,-320],[523,-977],[-467,-1020],[1080,-826],[-83,-788],[-2431,-1252],[-1520,406],[-2669,-616],[-849,-994],[-2465,-2088],[-2023,354],[-1085,512],[-4846,108],[-2493,-1088],[-1981,-663],[-1821,887],[-4139,84],[-2165,302],[-1608,603],[-7464,3224],[-1442,1283],[-63,1297],[-3095,4488],[-1258,1622],[362,867]],[[536376,903654],[-198,1820],[-852,1571],[-1126,1303],[-1633,1027],[-4067,1679],[-2968,364],[-3825,-374],[-3108,-782],[-4169,-2489],[-735,-546],[-1439,-1741],[-1877,-1038],[-1094,-188],[-2916,232],[-2448,569],[-2014,1243],[-450,928],[159,2125],[-620,1021],[-1225,1001],[-1658,604],[-2420,454],[-2137,212],[-2840,-421],[-1421,-505],[-2999,-1703],[-4642,-3012],[-1159,-928],[-1413,-717],[-2203,-488],[-3898,-415],[-3504,204]],[[471264,996647],[74148,-230],[33640,169],[24303,-116]],[[806098,969209],[-1345,-198],[-1394,-974],[-1195,-239],[-1542,-665],[404,-553],[-1734,-1284],[-1454,-296],[-1403,-1265],[-2493,-429],[-2054,-4039],[-34,-2844],[-2316,-3284],[-1632,-1631],[-3297,-4281],[-3664,-2088],[-5504,-159],[-15860,-15547],[-3331,-3321],[-1378,-1134],[-5338,-4997],[-24819,-12064],[-6213,-3051],[-3785,-1648],[-2604,-1417],[-4926,-2345],[-5231,-3821],[-1420,-1538],[-2548,-678],[-1326,-1031],[-2274,-146],[-15,-864],[-1543,-43],[-978,-612],[-687,90],[-2391,-899],[-733,254],[-1412,-123],[-2391,225],[-694,-233],[-959,-1070],[-2460,-433],[-2045,513],[-1496,144],[-1782,-252],[-1046,133]],[[673756,889072],[-1995,-801],[-1435,-290],[-1018,-797],[-2571,-437],[-1861,457],[551,2940],[-1916,1478],[-880,1321],[-1384,1354],[486,2836],[-1927,1416],[-53,764],[-1106,828],[-3957,83],[-796,857],[-1091,-1890],[-1417,-726],[-2758,-31],[2207,2584],[-1174,312],[229,1326],[-2507,1431],[-585,532],[1350,-162],[284,10275],[-27110,218],[-22713,-81]],[[603355,996470],[25099,-131],[99339,-463],[72178,-746],[1612,-6863],[675,-3741],[1181,-4496],[625,-2785],[2034,-8036]],[[291955,956629],[-638,-1112],[767,-1631],[-734,-1085],[-1482,-280],[733,-379],[-527,-491],[395,-686],[1502,-10],[1876,-628],[1101,-727],[-737,-1659],[-2529,-1297],[847,-1816],[-2389,-1670],[-194,-1740],[1571,-2108],[263,-935],[-3406,-1969],[-3416,-1556],[-352,-712],[125,-1255],[684,-1120],[1154,-991],[-135,-3469],[-327,-1060],[-3491,-944],[-1411,80],[-2497,622],[-1754,-138],[-795,-1199],[700,-986],[-1031,-1370],[-2992,-1526],[-2220,-1590],[-220,-1419],[-585,-1246],[-1427,-875],[-976,-1106],[1822,-1610],[82,-1515],[-677,-764],[-2105,-355],[-409,-1464],[-1457,-449],[-27,-337],[-1464,-18]],[[263173,908034],[-14221,221],[-6691,56],[-6266,203],[-3009,-21],[-9254,195],[-22016,381],[-32063,369],[-14698,206],[-9607,92],[-13364,395],[-10622,170],[-19421,616],[-3438,145],[-5554,58]],[[92949,911120],[1567,8371],[2602,12646],[1086,4794],[743,3801],[575,4697],[775,4066],[1668,9389],[1357,8016],[771,5380],[597,3568]],[[825472,899133],[-2085,370],[-1121,-561],[-146,-486],[789,-650],[-3239,-955],[-819,-1141],[-1067,-391],[-799,-1148],[-736,-143],[-1435,741],[-2069,-433],[255,-1925],[-698,-457],[-1716,88],[-1242,-915],[-1474,-559],[1506,-1099],[254,-2238],[-1142,533],[-1589,121],[-223,-516],[802,-765],[-417,-1011],[-1071,-106],[802,-1476],[295,-2507],[-1026,-1341],[-2006,-870],[480,-874],[-3313,-831],[362,-1141],[-1919,-721],[-1433,-1362],[-945,-2253],[-1133,-149],[-2139,797],[-24,-855],[1755,-1074],[-1159,-1228],[-1222,-167],[-386,-563],[448,-1288],[-1335,-474],[-748,-786],[-1278,-125],[-663,574],[-846,66],[-480,-1121],[-4559,-428],[-1325,-880],[100,-673],[-786,-290],[-433,-713],[-985,-629],[-147,-982],[-16365,-10399],[-10744,-6878],[-9729,-65],[175,-4060],[-2598,-111],[-1661,194],[-5614,927],[-55,-1757],[81,-7442]],[[733432,831532],[-8716,38],[-34866,-199],[-4914,68],[-6817,-9],[-7570,144],[-10297,122]],[[660252,831696],[-366,8828],[54,1422],[-558,19888],[-144,3125],[-178,14062],[14696,10051]],[[806098,969209],[1972,-7641],[4103,-15351],[3110,-10884],[4447,-15179],[1970,-7588],[2842,-9609],[930,-3824]],[[381611,932863],[-135,-9530],[-100,-10985],[-144,-5375],[-48,-7009],[-111,-6146],[-653,-17050],[-125,-5968],[-80,-389],[-10,-15158]],[[380205,855253],[56,-3024]],[[380261,852229],[-14633,-41],[-9773,62],[-16220,-50],[-13076,50],[-4815,104],[-15239,195],[-35181,768],[-8159,18]],[[263165,853335],[-138,9055],[-168,5581],[-57,6924],[56,4407],[272,12844],[-34,10163],[77,5725]],[[536376,903654],[-716,-427],[-2,-822],[-3367,-14119],[-1338,-5994],[-2147,-10217],[-1103,-4848],[-113,-12103],[-63,-1769]],[[527527,853355],[-3790,72],[-13251,87],[-7511,-5],[-1855,107],[-31973,307],[-6469,99],[-11276,96],[-19570,441],[-13557,225],[-33013,155],[-5057,314]],[[660252,831696],[120,-2856],[-193,-182],[-13075,202],[-438,335],[-2782,279],[-1070,-717],[-2069,-638],[-1513,-202],[-2339,63],[-1345,-1166],[-803,156],[-2063,-956],[-27488,-15521]],[[605194,810493],[-337,506],[-2026,1329],[-478,807],[-2119,740],[-2445,2032],[-8572,6540],[-3967,2915],[-9477,7194],[-10072,9300],[262,1995],[-2388,43]],[[563575,843894],[-476,831],[-524,14],[1446,2331],[-2390,6],[58,3037],[-4896,43],[-145,2794],[-8785,69],[-12364,148],[-7972,188]],[[263165,853335],[-9735,104],[-9543,164],[-10010,231]],[[233877,853834],[-23485,625],[-16566,189],[-12451,20],[-14671,169],[-17971,290],[-24593,505],[-13643,361],[-26934,772]],[[83563,856765],[2231,12938],[191,1530],[1734,10666],[680,4501],[1355,7696],[3195,17024]],[[857520,782347],[-2453,16],[-56,-762],[-4911,20],[-52,-746],[-19430,-33],[-148,-3026],[-9559,-203]],[[820911,777613],[184,3035],[-25243,1120],[-6500,331],[-6530,168],[-12678,658],[-7496,325]],[[762648,783250],[460,4401],[-2829,4057],[-2761,3663],[-9652,13420],[-1422,1923],[-162,1142],[659,1765],[1291,1688],[-96,600],[-1699,753],[-4148,-753],[-5923,-3160],[-2305,241],[-77,4752],[-552,13790]],[[825472,899133],[1770,-5545],[1243,-4386],[3623,-12095],[5438,-18843],[1271,-4965],[2007,-7293],[3960,-14686],[2241,-8446],[1952,-6965],[347,-2225],[2229,-8789],[3754,-14558],[239,-490],[1974,-7500]],[[233877,853834],[112,-17212],[-24,-2975],[-420,-14361],[-182,-3382],[70,-10502],[112,-6047],[-56,-9069]],[[233489,790286],[52,-18131]],[[233541,772155],[-28879,-108],[-2959,53],[-16991,469],[-14572,475],[-5197,-124],[-19501,226]],[[145442,773146],[18,8879],[-57,12429],[-9739,143],[-157,221],[133,5871],[-4984,112],[-4748,231],[-8033,99],[-11381,218],[-4947,54],[-4443,154],[-10275,132],[-12636,305]],[[74193,801994],[2019,12368],[2193,12024],[405,3081],[798,2848],[321,3579],[1096,6077],[2538,14794]],[[563575,843894],[-9553,185],[-1665,-1389],[-1439,-920],[-1154,334],[-331,473],[-2076,384],[-1108,-110],[-1310,-543],[-100,-819],[-1064,-873],[-439,-1371],[613,-421],[-332,-1270],[-571,-612],[-923,-237],[-2922,197],[476,-426],[-1587,-1685],[-783,173],[1052,-1108],[-2063,-1132],[-1046,-132],[1383,-1272],[-2054,-1222],[590,-1103],[1192,-278],[1129,177],[38,-460],[-1146,-801],[-1842,-475],[-1888,-1677],[-1101,-95],[-1722,-1448],[-517,-1193],[-1829,-788],[-886,-1781],[-1166,320],[444,-2035],[-1368,-262],[-1899,-712],[-1299,-1575],[1260,-941],[-1614,-501],[-1920,-960],[-2405,1796],[-899,4],[-1997,-978],[-2419,-941],[391,-693],[-560,-711],[-1245,490],[-2167,-156],[-989,-3240],[-568,-467],[-2717,-1252],[-1130,893],[-1129,-731],[-1611,-440],[-1005,-627],[-500,114],[-322,1302],[67,1253],[-1114,-99],[-1427,-1405],[-1475,-582],[-313,-585],[1230,-691],[2498,-2641],[1383,-946],[383,-807],[-750,-664],[-823,182],[-1689,1064],[-16,660],[-1957,-427],[-1586,-2136],[230,-1007],[1515,-750],[177,-1102],[-1864,-1258],[-987,27],[-1516,669],[-867,-138],[-1171,-1553],[500,-1033],[-1066,-529],[-4537,-1661],[-3,-700],[810,-713],[-367,-684],[-2723,-245],[-2325,-371],[-453,-319],[1043,-727],[-1422,-1260],[-4,-1772],[-501,-499],[-2660,-125],[-760,-597],[1357,-263],[337,-425],[-766,-358],[-2485,728],[-1043,-722],[-1849,-591],[121,-478],[1250,-545],[-814,-955],[-1067,-257],[-2505,609],[-2471,-195],[-1961,655],[-613,-24],[-654,-1075],[1500,-1808],[-758,-370],[-1379,421],[-2713,1500],[-1518,-272],[-5145,-2883],[144,-1318],[-5288,1452],[-1895,-474],[553,-2226],[-1149,-1355],[-2377,-130],[-3432,-745],[-2400,654],[-2566,-1806],[-450,-2022],[1725,-510],[377,-2222],[-1157,-1361],[1119,-849],[-1462,-365],[-2059,-941],[-2989,-105],[-950,228],[-1030,708],[-517,-727],[1388,-1176],[-688,-158],[-1158,665],[-2322,652],[676,-2034],[-998,62]],[[421142,760291],[-3237,461],[-1210,-240],[-3538,84],[-460,248],[-478,1371],[-1666,568],[-1550,-798],[-60,4682],[-23650,250],[168,711],[-2351,875],[542,789],[2706,439],[1732,643],[-1070,2632],[-2721,2375],[-2682,1055],[-214,1386],[259,588],[-1672,1363],[577,941],[-576,723],[-1995,914],[-2340,313],[-2211,-29],[-1214,824],[494,1571],[-1242,1114],[-264,637],[-2429,1632]],[[368790,788413],[10891,-174],[-45,1608],[125,14970],[-126,11093],[319,8882],[223,12218],[84,15219]],[[368790,788413],[-624,812],[-2509,759],[-1749,903],[-1191,43],[-1616,-512],[-2518,40],[-2126,-1989],[-832,-1663],[-1106,-258],[-1025,279],[-710,684],[-2348,839],[28,206],[-7879,143],[-4346,-21],[-30099,276],[-13823,-51],[-12847,239],[-10017,-18],[-20643,806],[-7559,189],[-4825,20],[-4937,147]],[[605194,810493],[-5359,-5616],[-2694,-5344],[-11,-8249],[-92,-4281],[-813,-476],[-405,-1365],[-1395,-95],[574,-1300],[-1233,-597],[23,-554],[-982,-277],[-1049,-741],[529,-744],[-2238,-723],[-1150,-1408],[-2000,-947],[-116,-507],[12227,69]],[[599010,777338],[-458,-684],[1389,-696],[-661,-881],[-861,73],[-2042,-1976],[-1365,148],[-1676,-1030],[-979,-1861],[499,-1252],[893,-768],[1233,-439],[145,-481],[-814,-1285],[-1849,-1282],[-636,-111],[-4531,-1821],[-728,-950],[-3019,-1655],[-2909,-1267],[-66,-681],[-1213,-1195],[-2199,-944],[-686,-687],[-4024,-1870],[-1938,-709],[-66,-639],[-2893,-71],[-1912,1218],[-1698,-636],[-1379,47],[-3042,-480],[-1006,-16],[-2643,-1171],[-1323,63],[-353,-427],[-3435,-173],[-1783,-821],[-297,420],[-1579,73],[-2798,-1898],[-15552,15],[-60,-6573],[964,-1099]],[[529660,740866],[-11030,0],[-5289,111],[-1783,765],[52,-742],[-2446,15],[-30,1473],[721,12],[-31766,14092],[-12448,138],[-8974,173],[-13461,206],[-6628,-2593],[-7972,-3197],[-4763,-3]],[[423843,751316],[2,3305],[-182,2859],[-2413,0],[-108,2811]],[[762648,783250],[-190,-1614],[-365,-5299],[-2253,385],[-12810,1595],[-4481,473],[-6202,1237],[-3600,887],[-58,-1509],[-9869,59],[-28,-1502],[-4965,-21],[28,-7630],[-9678,-1],[-56,3043],[-4826,-19],[0,-1523],[-4853,209],[0,-4524],[-4826,165],[1,-2901],[-2372,-38],[-56,-2940],[-222,-125],[-7113,250],[56,-3044],[-7671,251],[-84,-2315],[-4519,125]],[[671636,756924],[2599,621],[375,613],[-674,1953],[-1422,1043],[-1902,783],[-5000,-679],[-1810,28],[-1181,481],[-1548,2497],[-1655,1084],[-440,901],[828,3292],[-1483,248],[-2164,-808],[-1130,165],[-843,499],[-737,-173],[-551,-1002],[-766,-155],[-1184,394],[-998,1159],[-262,1500],[-1181,1628],[-1624,177],[-1817,601],[-1295,759],[-399,1409],[428,980],[-101,1809],[-507,1132],[-34,2231],[-1194,731],[-1180,-31],[-1075,889],[-2877,573],[67,2110],[-2009,353],[-654,812],[-2009,-478],[-2722,93],[-1334,-320],[-1595,-765],[-728,143],[-2843,-1603],[-2001,-732],[-1475,-1148],[-1157,1004],[-2139,341],[-1064,632],[-864,1940],[-1507,1001],[-634,-78],[-1172,-1127],[-2058,-2],[-1766,-1459],[-3336,-3147],[-1310,-956],[-1405,-171],[-546,-1085],[-1716,-1711],[155,-565]],[[145442,773146],[-79,-9360],[67,-3271],[833,-22792],[457,-10355],[216,-8636],[-64,-3694],[39,-24450]],[[146911,690588],[-14924,458],[-6812,161],[-7573,89],[-8418,311],[-12064,293],[-22719,502],[-11103,66],[-1044,105],[-6857,95]],[[55397,692668],[1105,6662],[972,5435],[1084,6907],[1972,11884],[1105,7804],[1242,6746],[1019,6199],[313,2921],[829,3168],[1271,7573],[967,4753],[1113,6620],[1047,5279],[550,3693],[1348,7103],[1880,10499],[979,6080]],[[423843,751316],[-17,-3023],[-4813,78],[13,-3068],[-9771,161],[21,-3056],[-4853,32],[-20,-6079],[-2328,0],[34,-3038],[-2525,-6],[236,-9100],[-4900,35],[-111,-6074],[-9747,106],[-10,-6051],[-14431,72],[20,-3083],[-9653,80],[-152,-3026],[-4845,12],[-306,-2198],[-1524,-1646],[-399,-1237],[434,-786],[1919,-1946],[2852,-1110],[67,-685],[-703,-433],[-2234,-161],[-1351,-499],[-2467,-1984],[-1481,-520],[-1349,78],[-3694,604],[-1574,-490],[-264,-2134],[-1845,-2100],[-883,-501],[-1647,68],[-383,284],[-1508,2422],[-612,455],[-1752,87],[-1105,-1289],[-86,-862],[788,-700],[1582,-732]],[[336466,688273],[-14312,257],[-83,15267],[-14645,-67],[-22,3051],[-9600,-27],[-5066,110]],[[292738,706864],[-40,18142],[-21244,521],[-7902,91],[-450,12106],[10,2413],[-434,13978],[-37,8109],[-8102,250],[-1040,-44],[-8816,263],[-11176,445],[34,9017]],[[671636,756924],[-404,-712],[2884,-1089],[780,-530],[601,-1215],[-633,-840],[-2733,-1945],[-394,-2292],[468,-1373],[948,-978],[1300,-747],[1479,-1397],[1353,-1625],[132,-1124],[-527,-804],[-3170,-83],[-1530,-466],[-2957,-1410],[-1989,-2028],[-1254,-432],[-3596,-862],[-3783,-1916],[-1703,-1248],[-237,-1493],[-1098,-808],[-2169,419],[-1512,653],[-2029,-1212],[-609,-846],[-197,-982],[603,-2447],[-40,-1330],[-354,-845]],[[649266,722917],[-1186,-1011],[-1311,-537],[-2063,78],[-2001,723],[-480,750],[-247,1868],[-800,1159],[-1510,958],[-1572,212],[-2396,-395],[-2074,-704],[-935,-911],[-228,-780],[822,-1601],[1512,-754],[3951,-1275],[1188,-583],[2988,-4158],[943,-2722],[-894,-1965],[-831,-1184],[-710,-438],[-6085,-242],[-1146,-435],[-390,-949],[1940,-1165],[1838,-552],[880,-584],[-907,-1458],[-5362,667],[-1552,391],[-924,-132],[-1203,-707],[-496,-711],[724,-1294],[2043,-1605],[-235,-1425],[798,-1260],[3754,-1455],[937,-732],[273,-944],[-377,-565],[-2516,-1443],[-2076,-692],[-1821,-1095],[-1988,-692],[-1045,-884],[-971,-2044],[-28,-2319],[-521,-456],[-2289,-690],[-1854,-207],[-1299,-696],[-1033,6],[-2227,899],[-541,1647],[742,885],[142,1187],[-1325,706],[-1681,-128],[-2465,-932],[-1216,-1019],[-322,-1939],[419,-972],[-569,-835],[-2117,-906],[-827,-887],[-1184,-1909],[-87,-1861],[-658,-696],[-4248,-2142],[-1092,-774],[-780,-1706],[-1860,-1590],[-631,-162],[-1144,-1812],[-972,-990],[-2542,-997],[-2048,-54],[-1692,-472],[-1575,-794],[-606,-1093],[-1180,-1095]],[[584215,662837],[138,4981],[-6,18262],[-17707,-23],[-11223,50],[110,9076],[-9829,-23]],[[545698,695160],[13,1529],[-7340,140],[-13,1482],[-2463,-32],[164,12311],[2391,-26],[-12,3010],[2413,16],[28,4540],[2410,-17],[21,9232],[77,4358],[-2450,10],[13,2957],[-2463,36],[-37,6157],[-8790,3]],[[746727,697304],[400,5914],[-128,200],[-14730,89],[-10843,-36],[-9117,30],[-6753,-45],[-14301,150],[-510,2861],[-338,155],[-6286,46],[-333,825],[360,1138],[-143,1076],[-1484,3318],[14,3188],[-1844,1030],[-1068,1028],[-2651,1496],[-691,1704],[-805,513],[-3550,81],[-8635,353],[-14025,499]],[[820911,777613],[-668,-10900],[-19350,126],[-13,-3079],[-9582,196],[-209,-172],[-33,-5964],[14484,-119],[-219,-9139],[-4856,53],[-20,-3043],[-4861,41],[-98,-3011],[-4689,-34],[-74,-4845],[-72,-12879],[0,-8323],[-2361,71],[-41,-1506],[-1141,7],[-4,-750],[-1187,33],[-73,-2286],[-5332,18],[-4394,113],[204,-3103],[-9763,131],[121,-2942],[-4946,121],[-65,-3761],[-456,-5399],[-3798,-31],[-10688,67]],[[857520,782347],[4859,-18563],[1113,-3972],[5726,-22505],[6746,-25647],[123,-326],[4824,-18292],[424,-1772],[2515,-9262]],[[883850,682008],[-1048,-271],[-1844,1258],[-1699,154],[-2837,554],[-3862,1377],[-328,523],[-1074,227],[-1093,-778],[360,-1053],[-10544,79],[-21774,360],[-13496,-15],[-13447,109],[-16384,79],[-5496,107]],[[789284,684718],[-12949,204],[-6603,229],[-14462,132],[-57,-3152],[-4758,33],[-12,-2979],[-7306,-24],[-7186,78],[-14808,-36],[30,1530],[4915,-3],[208,3089],[4710,15],[138,1463]],[[731144,685297],[793,354],[14568,8651],[222,3002]],[[292738,706864],[-17367,326],[-3917,242],[-8047,90],[-8638,249],[-6919,151],[-13134,554],[31,-6060],[-9770,-200],[-7,-12120],[-10955,-219],[-8566,-220],[-19349,815],[-9668,284]],[[176432,690756],[-4987,101],[-4590,-69],[-19944,-200]],[[545698,695160],[-116,-4551],[-7234,54],[-57,-1482],[-4820,46],[-27,-1434],[-2446,-6],[-73,-1512],[-1216,-19],[30,-774],[-1178,-11],[4,-711],[-2463,-3],[-2,-3023],[-2429,-18],[-1,-1492],[-2462,-32],[22,-1478],[-5712,-69],[-3684,29],[-10104,-77],[-8,-3083],[-4901,47],[-21,-1532],[-1174,14],[-10,-744],[-1199,0],[79,-2246],[-4851,90],[-107,-3014],[-9555,206],[-53,-3789],[-1166,9],[-90,-726],[-1177,-128],[45,-1401],[-4803,120],[-79,-4599],[-7194,129],[-41,-860],[-2446,53],[-21,-646],[-4688,37],[-101,-5982],[-14482,139],[-14,-1467],[-2432,30],[-22,-1524],[-1147,0],[-54,-720],[-1240,6],[12,-1482],[-2413,-6],[-22,-828],[-2362,-33],[-11,-747],[-1271,19],[-26,-786],[-1149,-7],[-24,-3823],[-2478,0],[18,-733],[-3601,0],[-67,-1526],[-5979,32],[-18,-1526],[-1233,-9],[-40,-734],[-1133,0],[-54,-768],[-1195,17],[-41,-1457],[-12261,95]],[[403430,632714],[-10848,93]],[[392582,632807],[-5,6053],[-2476,17],[8,763],[-3610,-3],[14,2296],[-10951,34],[-96,3160],[-5155,16],[-4581,107],[-46,3008],[-4871,21],[-104,4559],[-4854,24],[-48,3135],[-4834,38],[24,1560],[-4790,39],[-12,6079],[-4815,93],[170,3095],[-1412,-25],[-7,1564],[-3682,29],[41,1407],[-4864,210],[-24,3100],[-8376,239],[79,2922],[-5987,108],[17,2955],[-1725,15],[812,573],[1373,1524],[670,1090],[190,1276],[1194,325],[1656,-302],[1354,-892],[674,-37],[2089,616],[862,-62],[1128,-1704],[982,-528],[2130,36],[1018,1123],[-1127,1849],[-114,1291],[1324,556],[2201,-335],[1669,-777],[1281,33],[1222,795],[29,761],[-1761,1637]],[[731144,685297],[-6180,51],[-8599,-53],[-119,-9162],[-4864,-57],[-274,-12068],[-4753,-104],[-129,-2982],[-5134,-59],[-4667,83],[-86,-2788],[-639,-9395],[-362,-6097],[-9756,30],[-14181,166],[-9695,198],[-4797,48],[-383,-9632],[-113,-1290],[-201,-10304],[-1228,83],[-13349,162],[-344,-16823],[-84,-2200]],[[641207,603104],[-20677,-86],[-17348,-39],[-8734,-105],[-10780,-73],[-5032,173],[-9640,-88],[-16113,-95]],[[552883,602791],[1103,1617],[1823,1069],[2271,173],[2820,954],[600,567],[-6,1000],[-1714,1447],[-3945,1771],[-847,1315],[244,1246],[-1273,2076],[-1147,755],[-2433,414],[-930,531],[0,789],[3143,4221],[1524,687],[2633,-370],[1724,-870],[1589,138],[1113,849],[145,1149],[-1505,1958],[-48,1529],[354,1395],[1797,2202],[1428,705],[1734,-36],[2286,-538],[1567,508],[1148,1058],[1316,2097],[-6,738],[-612,930],[-1782,1558],[-434,972],[294,770],[1618,30],[1840,-1192],[2925,-788],[1393,-34],[2902,370],[4825,2508],[2930,693],[93,-159],[2826,1778],[-952,1951],[-1955,2304],[951,1911],[-91,742],[-1042,1143],[125,1279],[1687,971],[3237,60],[1660,289],[973,753],[-124,534],[-1829,2033],[-2136,1475],[-787,891],[-4931,1781],[-696,543],[-84,806]],[[392582,632807],[-3042,-17],[-7659,-5289],[-4855,3],[-100,2996],[-6033,72],[-14,-776],[-2377,3],[-13142,-7491],[-49,-6321],[63,-1828],[-51,-5590],[-1954,-6],[-12183,253],[-8910,254],[-8265,-8158],[-1806,-14865],[-135,-3431],[-15748,-415],[-13093,-170]],[[293229,582031],[-21775,194],[-15563,3],[-15264,83],[-2505,-20],[-11693,272],[-10872,166],[-4268,21]],[[211289,582750],[409,1398],[903,874],[-10879,-45],[-513,-49],[-22404,-3],[199,9460],[0,6512],[-2099,21],[94,5496],[315,6947]],[[177314,613361],[257,6812],[-99,6369],[-263,6678],[-181,6623],[146,2572],[-123,10089],[75,7519],[-69,2313],[60,4323],[-436,18819],[-242,2505],[-7,2773]],[[552883,602791],[-2742,-1744],[-1412,-359],[-1603,-768],[-147,-1435],[674,-1594],[783,-652],[-512,-1598],[-1094,-747],[-2139,-681],[-105,-651],[419,-1604],[845,-1050],[-292,-4262]],[[545558,585646],[-1918,508],[-3688,203],[-3009,-1100],[-1373,-125],[-2833,254],[-761,1308],[-1752,950],[-1627,389],[-2216,1742],[-2358,741],[-1495,811],[-668,1381],[-1599,45],[-2240,-255],[-654,670],[50,960],[788,492],[1670,401],[-197,877],[-3662,9],[-12168,-86],[-14938,-51],[-8720,-2],[-10925,-54],[-9489,-99],[-9,352],[-10731,326],[-5105,16],[128,-4578]],[[444059,591731],[-4836,-18],[-21,1510],[-4915,18],[-25,814],[-1026,-2],[-46,684],[-3855,-54],[-5,3074],[-4913,-12],[202,4137],[-5135,-39],[24,5567],[-101,6887],[-1240,20],[-531,729],[-7796,60],[8,789],[-6069,0],[-12,5347],[1210,1],[-23,3823],[-1209,-12],[-69,4446],[-246,3214]],[[177314,613361],[-2825,-1353],[-1125,-81],[-91,-592],[-1412,-669],[-1276,708],[-1633,-798],[-2097,-406],[-441,191],[-1503,-773],[-867,-780],[-1441,-410],[-707,186],[-2688,-541],[-888,-779],[-145,-634],[-1769,472],[-1944,-535],[-881,-641],[-1041,545],[-652,-818],[-1108,-582],[-660,200],[-2172,-1434],[-1145,36],[-697,-720],[-340,-1314],[-1001,-1199],[-896,-335],[-113,-875],[-1579,53],[-1326,-1143],[-408,-840],[-2194,41],[-175,392],[-2528,-556],[-734,-636],[-1867,-131],[-842,-574],[-1443,610],[-1275,-634],[-2568,-839],[-1373,-200],[-2194,-944],[120,-521],[1008,-384],[-501,-538],[-1070,-215],[-787,1018],[-1070,177],[66,-1055],[1380,-1502],[401,191],[393,-1084],[-1282,-276],[-1228,159],[-1163,-1396],[-2525,503],[-781,345],[-623,859],[-1585,1053],[-135,673],[-1806,-96],[-1563,383],[-880,-706],[583,-463],[1078,443],[190,-989],[-1917,-486],[-466,746],[-653,-120],[-204,-702],[1493,-573],[-1738,-588],[-1547,545],[-659,-588],[-3430,-38],[-1760,680],[-729,559],[-1386,45],[-1707,-320],[-2,-448],[-1687,-481],[-1506,231],[-107,776],[-1305,-62],[-6,-851],[-904,474],[-1145,-482],[880,-1119],[972,-630],[175,-559],[-3353,-1204],[-1356,-153],[-1760,-1094],[-1822,-2225],[220,-1478]],[[84061,580463],[-17029,-200],[-21579,-574],[-8414,-197]],[[37039,579492],[223,1861],[2410,15117],[1830,10946],[669,4343],[1367,7957],[530,4003],[753,3671],[501,3454],[1758,10597],[7133,44159],[1184,7068]],[[883850,682008],[2221,-8830],[1162,-4141],[3830,-14765],[6395,-25011],[2354,-9443],[1656,-6192],[2483,-9765]],[[903951,603861],[-37396,74],[-22431,125],[-6109,1],[-14219,-78],[-5234,-110],[-15247,-165]],[[803315,603708],[-16831,-147]],[[786484,603561],[-120,3012],[243,18980],[1189,-17],[152,3014],[-1244,23],[185,5121],[321,6076],[125,5390],[2519,-41],[66,2309],[-1217,-13],[14,747],[1163,-11],[58,716],[-2448,58],[601,8825],[423,4162],[488,9069],[97,10655],[185,3082]],[[786484,603561],[-4874,-13],[-21332,-263],[-5381,-105],[-9684,-106],[-14563,31],[-4782,84],[-7789,39],[-21184,50],[42,-3080],[-7086,41],[-2566,-92]],[[687285,600147],[-44,2969],[-445,28],[-21008,14],[-24581,-54]],[[444059,591731],[1204,6],[118,-10387],[68,-22353],[50,-5832],[-52,-5977],[-7945,245],[-13348,73],[-7972,-109],[-5426,27],[-5182,-75]],[[405574,547349],[-6395,-90],[-15646,-125],[-7479,-127],[-8451,-23],[-4661,108],[-6914,-123],[-7495,-14],[-2908,-604],[-4437,-104],[-19298,-48],[-89,9091],[-4555,-69],[-23811,-58]],[[293435,555163],[298,5857],[-180,4102],[52,10282],[-182,4861],[-194,1766]],[[211289,582750],[519,-1011],[2150,-1219],[-298,-1217],[-1214,-827],[-2510,-153],[-1748,174],[-1641,-1459],[-432,-830],[-840,-125],[-983,813],[-1889,77],[-818,-428],[1108,-821],[-293,-1192],[755,-935],[1300,-358],[440,-470],[-2351,-818],[-631,-597],[868,-730],[1470,551],[1728,301],[979,-237],[230,-775],[-2733,-2346],[-755,-273],[-2278,-8],[-1601,323],[-1986,-944],[-303,-1558],[-695,-146],[-874,678],[-1232,-65],[-88,-1230],[1146,-560],[602,-821],[1372,-1046],[-710,-1918],[-566,-271],[-1062,242],[-3358,-1106],[-3702,42],[-2028,-941],[-478,-709],[-1377,100],[-1014,895],[-945,-134],[126,-609],[2208,-803],[0,-1208],[-618,-203],[-969,604],[-1642,11],[51,-1762],[421,-1521],[-701,-197],[-2374,206],[-377,-296],[-56,-1309],[664,-692],[2373,-206],[472,-777],[-1062,-251],[-2010,36],[-559,-1046],[713,-720],[2412,-523],[1489,-961],[-424,-1381],[844,-597],[-625,-1778],[1400,-837],[-410,-529],[-1443,-396],[114,-1608],[-1412,-1079],[-1411,-161],[-950,-474],[-1008,-1665],[-3071,-1057],[-1436,-947],[-1278,-115],[-2143,282],[-574,-135],[-359,-1314],[-799,-786],[231,-373],[2410,-839],[3191,564],[3917,27],[356,454],[-363,1332],[1675,251],[1748,-750],[4834,-3385],[473,-841],[-66,-784],[-737,-1667],[-366,-216],[-2615,246],[-2234,-618],[-1106,-1330],[-510,-1864],[438,-786],[1703,-1063],[2868,56],[1698,1327],[2475,576],[815,-203],[765,-1748],[-856,-1030],[130,-1479],[649,-1085],[2006,-1607],[-4,-1233],[-1993,-1653],[-129,-623],[906,-1651],[797,-621],[1221,-357],[4409,-553],[2131,516],[2222,1481],[1303,-307],[806,-543],[299,-1172],[-664,-1147],[-1795,-2029],[-911,-214],[-1940,552],[-2793,1072],[-1038,81],[-2051,-544],[-2828,-400],[-4457,269],[-894,-689],[-128,-622],[1407,-1363],[473,-1445],[2239,-1724],[830,-386],[3346,-707],[2233,668],[1580,177],[2066,819],[2033,271],[1610,-192],[184,-799],[1233,-2299],[1962,-1750],[-28,-352],[-2317,-347],[-2881,-1105],[-1855,-2474],[-1771,-350],[-574,1004],[329,1163],[-503,606],[-2611,851],[-1659,-462],[-172,-1540],[388,-1439],[-658,-1725],[-744,-223],[-999,974],[-1115,-176],[-617,-1123],[519,-790],[414,-2177],[-596,-1569],[-902,-767],[-1674,-880],[-991,-812]],[[184276,482199],[-503,-896],[-1305,-461],[-1307,682],[-82,1240],[280,1114],[1817,1005],[-1390,1179],[-1945,499],[-2313,-33],[-2044,400],[-1879,-1765],[-726,-1395]],[[172879,483768],[-2021,20],[-684,221],[-3104,2451],[-180,824],[658,1751],[-449,708],[139,1621],[-1759,2170],[-2614,1769],[-2268,908],[-316,1467],[1013,818],[1885,305],[1381,1084],[2302,66],[2295,-192],[1192,-357],[-599,-1811],[1240,-1563],[669,-277],[940,352],[858,1497],[1767,386],[1149,1144],[-1267,1114],[-2109,607],[-1429,1412],[-5332,269],[-1338,-253],[-2057,-763],[-4304,-549],[-939,1263],[-1256,960],[-1842,965],[-2001,421],[-1179,-17],[-2836,-1082],[-1928,23],[-5916,-2129],[-2878,-1398],[-4834,-978],[-3911,-976],[-6204,-251],[-1929,-293],[-3750,-1037],[-1466,340],[-913,1650],[-2611,2133],[-2221,1442],[-604,1620],[488,2076],[818,771],[1251,250],[2854,-334],[1283,484],[703,857],[616,2725],[-238,721],[-1422,1625],[426,974],[4015,2049],[595,678],[-1449,1100],[-1893,624],[-785,-221],[-1337,-1190],[-2913,-886],[-3042,-589],[-3189,35],[-2313,619],[-2798,980],[-1520,1556],[601,637],[3647,42],[3784,1234],[961,726],[821,1995],[-2317,2169],[-3114,1554],[-1660,2372],[-73,2288],[-792,1641],[310,747],[1021,1022],[1462,555],[2566,-317],[3079,-1212],[1050,313],[1252,1485],[1169,568],[859,1374],[-424,770],[-1739,1942],[-542,343],[-1419,-214],[-4019,-1419],[-1707,-490],[-1629,571],[-486,932],[-1083,1027],[-1894,938],[-1064,870],[-679,1216],[-1590,1658],[-1078,764],[-1244,143],[-1815,-668],[-891,-1342],[-1828,-119],[-1080,424],[-863,806],[-3274,-567],[-1523,263],[-948,1294],[969,720],[1817,-219],[1633,257],[2013,1524],[752,905],[489,1490],[-1192,831],[-2029,-53],[-1165,1057],[-1249,747],[-1806,670],[-599,1212],[83,2857],[-1091,1947],[-805,1877],[-1559,632],[-1121,136],[-1650,899],[-536,1365],[2034,1051],[2600,523],[3290,-301],[1186,360],[883,1304],[-287,767],[-2808,583],[-1349,1326],[-413,1473],[1288,696],[527,-87],[1464,-1096],[2039,-501],[1211,-10],[2013,1372],[225,750],[-3014,1442],[-281,2324],[-951,1098],[174,1673]],[[903951,603861],[6009,-22407],[2145,-7920],[920,-3648],[4122,-15246],[345,-2239],[1284,-1135],[2884,-571],[1320,779],[1468,-386],[1610,-1582],[-49,-1492],[-2373,-847],[-772,-509],[-792,-1353],[984,-1538],[-333,-1023],[289,-823],[1521,-1449],[1831,-864],[1797,-72],[1703,-1560],[97,-1192],[1405,-348],[918,-826],[1621,-338],[920,-1259],[-457,-311],[-3891,-1118],[-951,-622],[-100,-1037],[1664,-2446]],[[931090,528479],[-32038,-281],[-9736,-11],[-56,-3003],[-9595,0],[-15481,-93],[-8256,52],[-84,1501],[-2398,-62],[0,1521],[-4771,63],[0,-3065],[-3736,-21],[-10628,62],[56,1523],[-2483,-21],[28,-1481],[-21596,-334],[-1,1559],[-2419,-30],[-26,-1565],[-4548,-67]],[[803322,524726],[26,12253],[-167,9951],[16,8449],[152,14881],[-97,9638],[115,4786],[-52,19024]],[[803322,524726],[-4742,-83],[-28,-2961],[-19413,-292],[36,-3044],[-4750,-105],[-56,-6067],[84,-6005],[222,-9089]],[[774675,497080],[-4713,-42],[28,-2898],[-24003,-176],[182,-9123],[252,-8966],[-14338,-62],[-10454,-192]],[[721629,475621],[-990,860],[-445,1584],[444,1864],[-450,1057],[1243,3839],[-248,517],[428,2262],[-1002,2751],[-230,1121],[276,1615],[-620,1540],[-269,2124],[-602,910],[-146,1614],[249,2195],[758,1976],[540,2175],[6,1025],[524,1098],[-181,670],[-2463,1348],[-2508,2326],[-259,1201],[-1117,1099],[-159,1301],[547,1727],[-227,1383],[784,397],[1323,96],[2470,1388],[394,578],[454,1917],[834,445],[45,1497],[1760,1171],[326,1664],[-606,645],[-1374,91],[-1362,908],[108,555],[-17451,54],[-196,2982],[-4797,21],[166,-2982],[-9768,12]],[[687838,530242],[-7,7621],[620,1488],[944,431],[-1498,331],[-133,2058],[-1693,1625],[552,682],[1130,298],[-1669,230],[289,448],[1358,-35],[32,4017],[-100,5860],[-25,6527],[-120,7525],[0,12321],[-233,18478]],[[687838,530242],[-11239,12],[-19706,-90],[-7898,-107],[-2333,39],[-12040,-54],[-2408,-104],[-20714,-19],[-10770,54],[96,2948],[-4889,61],[-28,-2991],[-10656,-42]],[[585253,529949],[-4402,1076],[-1324,662],[-1128,1360],[-2676,1694],[-720,1019],[-181,958],[-603,696],[-1815,509],[-1899,-12],[-1003,825],[-3824,2162],[894,837],[-320,624],[-1838,-146],[-1456,117],[-805,498],[-540,2400],[-529,902],[223,1117],[1425,2040],[2344,930],[-226,1461],[-1439,1536],[-2109,790],[-3099,141],[-941,191],[-1352,768],[-545,1586],[-2020,3176],[-258,1541],[-1292,1158],[-2879,470],[-496,1109],[-1250,893],[-1011,1061],[-276,912],[580,1370],[-688,1108],[351,2448],[-585,1878],[528,1701],[1098,1263],[137,1683],[-3007,3369],[694,3006],[567,810]],[[585253,529949],[1064,-589],[-11765,-35],[62,-9008]],[[574614,520317],[-7395,173],[-14334,-148],[-2498,-72],[-15272,-48],[-18390,-140],[-1204,29],[-24892,-146],[228,-8990],[-423,-178],[-9781,-154],[-18574,-182],[-27343,885],[-656,-42]],[[434080,511304],[-9988,-24],[-13172,-158],[-4927,-3],[-31,13730]],[[405962,524849],[-33,6430],[-250,13443],[-105,2627]],[[293435,555163],[-113,-7264],[61,-1844],[-14165,-43],[-124,-2855],[108,-5973],[-47,-7955],[57,-1392],[-450,-3185],[-31,-15076],[-14303,-32],[-26,-18242],[141,-6273],[-35,-4653],[118,-7046]],[[264626,473330],[-24417,-78],[-3621,-81],[-10655,-110],[-11746,-12],[-6534,50],[35,9082],[-23412,18]],[[172879,483768],[1798,-290],[1550,-923],[-240,-1144],[-673,-619],[-2515,-601],[-4087,482],[-2136,641],[-7425,608],[-2766,-903],[-1634,-911],[-1841,-1819],[-1636,-1180],[-3983,-1910],[-2535,-3859],[-1074,-810],[-4497,-2256],[-1634,-307],[-3198,-95],[-1970,-631],[-2754,-1772],[-3228,-959],[-3235,-1279],[-866,-553],[-1361,-1715],[-517,-1365],[-387,-1950],[-614,-4908],[-393,-1372],[1714,-956],[5241,-251],[931,-233],[2986,-2391],[1922,-970],[1158,-1033],[3516,-1237],[998,-54],[1812,403],[1722,-564],[1052,-1817],[465,-287],[2847,-598],[1576,-1346],[756,-1223],[963,-603],[2648,-625]],[[151335,437583],[-20802,-262],[-19856,-75],[-20617,-111],[-16392,-179],[-14889,-14],[-5541,76],[-9798,-44],[-6821,99],[-14937,104],[-7242,10]],[[14440,437187],[2129,13604],[369,1271],[847,4800],[1571,9551],[310,2680],[1546,9775],[1395,8297],[4782,30496],[472,3582],[1391,7470],[13,516],[3734,24378],[202,1850],[3838,24035]],[[405962,524849],[-710,-857],[-462,-1638],[-1649,-1801],[-83,-597],[-1900,-3956],[-107,-840],[1307,-1501],[-211,-622],[654,-798],[-1287,-2376],[-2255,-2527],[-998,-1577],[-291,-2459],[346,-2728],[1260,-970],[444,-1162],[-961,-1561],[-1276,-211],[-2115,-964],[-691,-1040],[-1002,-305],[-3957,-2020],[-1706,-606],[368,-909],[-512,-965],[1259,-869],[281,-977],[-142,-1487],[-1161,-1539],[-980,-48],[-1866,-1267],[-259,-1509],[-1703,-1207],[422,-956],[-973,-244],[-827,-1700],[284,-350],[-1984,-1252],[59,-779],[-694,-750],[-3829,-436],[-26543,-123],[-3806,-547],[-16438,-137],[-12824,-173],[-6707,35],[-3414,-44],[-13433,26],[203,-13103],[8,-5202],[-128,-4086],[57,-5551],[253,-8517],[-14293,-102]],[[278990,436965],[-14308,-68],[-134,7345],[-255,7763],[361,2094],[-28,19231]],[[721629,475621],[1946,-890],[948,-852],[2243,-888],[1684,-218],[1720,227],[781,-961],[-936,-188],[-1497,337],[-3072,-531],[-630,-246],[-1046,-1694],[-167,-1345],[-880,-612],[693,-758],[-2564,-855],[-1596,1],[-1959,579],[-2646,-21],[-3185,305],[-1309,457],[-1497,-164],[-3250,-1837],[-2766,-711],[-1694,166],[-661,1306],[-2840,1084],[-1182,210],[-901,-361],[247,-780],[1296,-771],[-1044,-720],[-1703,-386],[-1493,1362],[185,1094],[-713,257],[-1334,-1438],[261,-701],[1470,-1494],[-656,-1141],[-1024,-472],[-1713,-84],[-1044,281],[-1050,-248],[-1166,-948],[-1664,-654],[-798,75]],[[683423,460393],[-1700,538],[-2345,-215],[-1720,-992],[-326,-689],[270,-1149],[-720,-414],[-2346,432],[-2320,153],[-4105,795],[-2785,1921],[-1349,-544],[-1330,-176],[-1786,117],[-1372,-173],[-1387,-514],[-675,229],[-142,1166],[-731,391],[-1015,-802],[-1659,372],[-241,568],[1484,1350],[-238,596],[-1537,-663],[-2000,-160],[-1559,-792],[-1563,-320],[-1037,69],[-685,938],[321,928],[-1888,254],[-1179,735],[-3181,312],[-1526,-1112],[-1258,-496],[-1010,-15],[-1316,1691],[1960,427],[1936,795],[-2187,2011],[-1205,-185],[-1704,-917],[-719,232],[-699,1097],[-1994,1920],[-1,1262],[-1213,289],[-1167,-977],[-847,-286],[-1099,202],[-493,726],[247,843],[1779,858],[-2605,2037],[-873,-206],[-40,-499],[-1457,332],[754,1266],[-2006,314],[-1062,-63],[-1118,861],[-2911,349],[-1330,-30],[529,-876],[-272,-641],[565,-642],[1084,-306],[78,-1322],[-1776,-1095],[-5232,99],[-1281,-890],[-1727,215],[-1433,1250],[-15,686],[-1739,926],[-1321,138],[-547,-1043],[1357,-1455],[286,-1335],[-153,-1201],[-1969,-3057],[-887,-549],[-1843,-487],[60,-924],[1125,-310],[1463,-804],[956,-824],[582,-1327],[951,-1377],[-454,-971],[-861,-655],[-1323,374],[-163,801],[-978,693],[-3307,1081],[-1219,762],[-2877,894],[-1295,30],[-1586,-622],[-3515,0],[-1405,-144],[-3547,-672],[-1678,266],[-1146,-86],[-520,-625],[953,-849],[111,-875],[-882,-786],[-2684,-251],[-722,-295]],[[575156,458299],[-139,8466],[-84,8363],[-104,2707],[38,5015],[-111,18350],[-50,1968],[-92,17149]],[[931090,528479],[1313,-534],[1899,-248],[2114,-547],[1040,-978],[-190,-1030],[-1530,-1189],[-292,-2321],[830,-652],[-155,-836],[1158,-2058],[-164,-1626],[1895,-1236],[801,-58],[2591,-1881],[1016,-1342],[-93,-1236],[791,-368],[222,-750],[-1008,-322],[-2992,-1534],[-455,-758],[1765,-1199],[2032,-486],[1935,454],[134,-1350],[-1679,-909],[-69,-617],[2156,-1285],[854,-1622],[-775,-350],[840,-1114],[848,-2008],[2519,-2723],[1097,-292],[1108,-714],[1584,-1443],[2204,-1006],[656,-839],[2700,-1494],[1089,-1180],[2272,-644],[478,-1305],[1462,-1123],[661,-810],[953,-212],[1044,-1177],[1492,-1141],[-902,-234],[136,-901]],[[968475,479251],[-16702,-28],[455,-7794],[-16745,-296],[-36584,-314],[-12833,-178],[-10417,-102],[1031,-12043],[-12495,-134],[-16484,-102]],[[847701,458260],[-198,4180],[-691,10539],[-375,3493],[-14161,-33],[-13454,4147],[-4081,1306],[-16174,5004],[-5155,1532],[-9030,2815],[-56,3002],[-9595,-63],[-56,2898]],[[434080,511304],[-969,-920],[-83,-1070],[1079,-296],[-14,-669],[891,-248],[-242,-454],[-989,-83],[-271,-454],[847,-1285],[703,-176],[611,-1399],[-407,-1200],[168,-1118],[612,-286],[-60,-942],[-514,-305],[1510,-926],[-406,-441],[596,-912],[-97,-759],[536,-687],[-181,-1263],[520,-239],[-294,-677],[1421,-1337],[-650,-497],[159,-1105],[733,-606],[-604,-1496],[106,-616],[-1434,-1521],[-361,-1284],[868,-491],[-897,-340],[143,-496],[899,42],[444,-864],[-247,-650],[393,-679],[1569,-974],[423,-1569],[753,-194],[303,-678],[-54,-1706],[921,-328],[1298,-990],[-377,-1009],[1243,-621],[-196,-778],[-889,-158],[370,-641],[3060,-2722],[-150,-602],[604,-1233],[1325,28],[1146,-1725],[-1681,-1341],[-143,-1177],[2194,430],[990,-562],[508,311],[1348,-239],[2346,-1378],[3069,-502],[1304,-790],[-111,-440],[-1123,-484],[-2711,-177],[-1559,-591],[-529,-1255],[740,-2282],[1210,-1124],[1190,-704],[1414,-1981],[888,-763],[2559,-1077],[678,-487],[2100,-3233],[169,-800],[-589,-1094],[-1665,-1030]],[[462544,443885],[-5164,-1369],[-4739,-1102],[-26,-3982],[3734,-219],[3114,-598],[-1879,-1323],[-759,30],[-2257,-1362],[-1280,-236],[84,-935],[-730,-311],[-940,176],[-1253,-654],[81,-866],[-1381,-608],[-365,-1209],[634,-911],[1648,-950],[384,-1246],[2407,-1658],[723,-287],[560,-971],[1629,-269],[347,-803],[4142,-670],[2525,818],[43,-2682],[-3244,74],[-7496,18],[-5812,-68],[-8164,66],[-2664,-33],[89,-3439],[-94,-3331],[214,-3284],[-13,-8098],[219,-9851],[69,-6865],[-59,-2048]],[[436871,382829],[-14721,-67],[-8052,-86],[-3176,92],[-33050,-89],[-1816,80],[-14807,-24],[999,1270],[-910,454],[533,1611],[-1157,812],[-2030,144],[-1935,1541],[736,257],[599,800],[-436,840],[-1420,-44],[-1412,1328],[-1090,601],[-727,-278],[-4332,257],[-1645,726],[-1401,977],[-1250,1440],[123,836],[-838,837],[-1421,846],[-1979,457],[-2478,197],[2187,1530],[521,705],[298,1457],[-3211,896],[-2823,401],[-2270,-658],[-557,189],[-9,791],[-1293,1833],[-307,941],[-997,1110],[-1444,-913],[-1233,20],[-21,421],[991,386],[-1577,-60],[277,460],[-1118,1279],[-1428,391],[679,1214],[-1037,588],[59,-846],[-1007,-334],[-1705,669],[-60,1263],[662,945],[-1164,1079],[-106,-640],[-842,-204],[-692,574],[-615,-178],[-2203,775],[-901,-555],[-129,526],[-1367,-406],[-1482,355],[-863,-785],[-1992,86],[744,364],[209,703],[-1270,0],[-1947,1514],[54,1829],[-399,770],[-3864,171],[773,469],[-233,1533],[-565,779],[-1226,473],[-2404,-673],[-2703,601],[-894,941],[-2267,304],[-724,1073],[-1025,671],[-1452,535],[-926,715],[-122,1410],[-1806,755],[-2689,-163],[-1192,-959],[-1914,-34],[-1949,333]],[[279208,428063],[-218,8902]],[[575156,458299],[-3130,-1224],[-1675,-499],[-3368,-338],[-1711,54],[-1843,1064],[-1108,149],[-1059,-327],[122,-1323],[-312,-1428],[14,-1738],[-312,-1165],[-1524,-613],[-1176,-1058],[-100,-624],[-1035,-436],[-2547,582],[-1765,-546],[-258,-562],[532,-1402],[-48,-1603],[-1573,-619]],[[551280,444643],[-5331,-630],[-3703,-610],[-1883,276],[-1025,1197],[-50,1266],[-736,2492],[-941,927],[-1342,268],[-2116,-129],[-930,216],[-2337,1118],[-2795,96],[-883,-287],[-1452,-1225],[-179,-1001],[-1518,-446],[-1462,828],[-1290,317],[-2978,1580],[-458,819],[851,2210],[-52,2055],[-1277,1474],[-1063,170],[-1105,-616],[-1901,-355],[-3425,81],[-2113,-894],[-412,-1553],[546,-535],[-471,-1655],[-508,-836],[-1721,-1077],[-2294,-1806],[-2727,-1620],[-1464,-251],[-3058,819],[-3362,472],[-1683,761],[6,577],[-1675,1892],[298,1377],[-169,2404],[572,439],[154,990],[-675,777],[-956,322],[-1249,-212],[-388,-607],[-1492,-961],[-3188,-1357],[-2882,-191],[-1287,78],[-1993,938],[-2267,244],[-1758,-788],[438,-1237],[-439,-2025],[-90,-1389],[1357,-2056],[1020,-2614],[-240,-1536],[-596,-1148],[-974,-1150],[-3396,-3208],[-1726,-594],[-2238,-300],[-992,57],[-1897,617],[-1094,1857],[131,2753],[349,638],[1248,739]],[[847701,458260],[84,-5464],[-163,-4057],[-118,-9915],[229,-11556],[-53,-2285],[161,-3260]],[[847841,421723],[-483,27],[-18039,-51],[-14879,-216],[-9779,-44],[-10208,84],[-42649,-42],[-4769,-84],[-16617,-182],[-3623,1575],[-802,1481],[-1722,-42],[-387,1205],[316,1170],[-632,651],[505,1189],[999,467],[-420,880],[1127,-14],[-1834,2942],[-23,898],[-1325,711],[-1587,134],[-1497,568],[-543,1428],[-653,-4],[-220,-3340],[68,-2960],[-5767,-120]],[[712398,430034],[-423,1356],[-1443,333],[-1152,635],[-2047,325],[-955,452],[-3765,2698],[-129,1152],[-656,511],[375,1285],[-846,1623],[-2127,232],[-403,890],[317,467],[-717,392],[-4207,93],[-1123,128],[-1115,744],[-816,1787],[632,373],[-565,549],[336,1882],[-1715,461],[0,1086],[-1147,171],[206,634],[-2499,2351],[-693,361],[884,1022],[297,1051],[-850,496],[0,1202],[710,289],[-1053,1094],[-1754,901],[-532,1333]],[[279208,428063],[-1195,579],[-1807,-317],[-1361,410],[-3724,-24],[-3370,-358],[-1580,-987],[-1243,-1407],[120,-1900],[119,-11269],[175,-8708],[-32,-3565],[-16469,-33],[-11973,-62],[137,-7568],[2,-4506],[155,-7423],[54,-6955],[-627,6],[-11976,-697],[48,-2253]],[[224661,371026],[-22938,-260],[-11051,73],[-16477,-6],[-4686,27],[-19613,-136],[-21609,-15],[-10165,18],[-6627,55]],[[111495,370782],[-2624,1578],[-1494,1750],[-1014,212],[-643,-755],[932,-1392],[-492,-750],[-684,-41],[-2498,786],[-1157,691],[-1559,1334],[-1056,2106],[83,943],[744,1538],[309,2665],[-1172,1533],[-233,774],[1060,1076],[3706,1855],[1812,773],[2160,254],[1097,-215],[1615,-716],[1337,-939],[1655,228],[1421,1583],[1246,905],[3625,1545],[27,1299],[-702,1154],[-1597,1478],[516,1366],[2040,2467],[1008,4443],[885,689],[1808,88],[1712,-302],[664,281],[1049,1284],[1854,3872],[913,2447],[10,1945],[-1473,2417],[239,856],[1027,1417],[213,1276],[-577,1318],[-1378,1571],[-157,1323],[1805,1927],[134,1308],[-286,1303],[-2166,1297],[-905,1046],[218,2565],[1193,172],[1758,-619],[1142,98],[46,655],[-697,1034],[180,728],[1158,516],[3397,-549],[2673,2461],[1378,294],[1224,-854],[669,-929],[1020,-500],[1388,57],[2318,744],[1320,797],[1603,97],[1173,-613],[76,-977],[-625,-1228],[-1710,-1196],[403,-731],[1487,-132],[2141,359],[687,1067],[-847,1464],[-57,818],[830,1795],[-545,517]],[[968475,479251],[1170,-335],[400,-1243],[-265,-2154],[613,-1338],[-499,-709],[359,-1236],[-798,-1381],[-160,-1365],[1104,-2688],[5549,-1694],[1239,-541],[740,-967],[228,-948],[860,-1673],[-2173,-1281],[-2341,-959],[-301,-1869],[845,-1023],[2211,-697],[221,-750],[-673,-233],[-3419,248],[-1055,-825],[-147,-1034],[931,-324],[2611,8],[894,-517],[-842,-899],[-2261,-60],[-959,-806],[851,-995],[-208,-633],[-2453,-1826],[-1962,-931],[-1202,-843],[-811,-1467],[173,-1990],[457,-683],[1317,-661],[3473,-676],[5078,-1473],[3317,-781],[1268,-509],[2014,-212],[3250,-1141],[3371,-2904],[2599,-1491],[2290,-734],[1793,-1234],[753,-54],[2074,-1171],[-340,-851],[-933,-186],[-1256,490],[-3153,-1237],[-1633,-813],[-143,-1966],[-520,-866],[-1786,-1159],[-141,-1467],[-1362,-804],[-3374,-514],[-2355,144],[-3961,-48],[-1713,210],[-1431,-460],[-1394,-972],[-281,-797],[973,-807],[2832,18],[1013,-837],[-375,-1045],[-2721,-875],[-1859,-344],[-5301,-1356],[-2316,-260],[-1334,-666],[-1507,-1358],[-2746,-1750],[-1396,-1479],[-3931,-3076],[-2216,-828],[-1595,-872],[88,-741],[1359,-2740],[199,-989],[1715,-3600],[566,-833],[-120,-894],[-1162,-708],[-983,-1933],[295,-842],[-551,-1462]],[[953150,385976],[-4211,19],[-9453,-128],[55,1505],[-2345,-38],[-53,-1497],[-20011,-126],[-1911,618],[-55,959],[-742,57],[-309,1066],[758,502],[-1848,1163],[-1952,845],[-1179,1375],[-841,415],[-1097,-278],[-2907,1580],[218,756],[-702,1847],[-1141,382],[11,756],[-3144,-84],[21,891],[2548,74],[-1603,1237],[-2208,242],[-1003,1057],[-1735,556],[-5,1013],[544,932],[-4296,24],[-14282,-186],[-14085,10],[-9847,-116]],[[854340,403404],[-4797,-21],[-711,8032],[-258,2035],[-733,8273]],[[712398,430034],[-18807,-422],[0,-4525],[-3514,-21],[643,-41593]],[[690720,383473],[293,-10614],[125,-6797],[-3272,-51],[-31953,-15],[-924,-100],[-18528,-63]],[[636461,365833],[-14053,-47],[-16861,-241],[-116,15018],[-274,3027],[-2499,20],[-17404,-166],[-8733,-39]],[[576521,383405],[-104,6214],[3,3776],[-335,10533],[-122,12534],[-133,7360],[-736,165],[-98,640],[-1878,-732],[-1317,741],[328,1051],[-2378,1064],[-1300,-134],[-1687,812],[-660,-176],[-1341,457],[-69,937],[-1896,1160],[-2242,-30],[-2294,-719],[-1783,453],[-107,760],[-1311,1280],[-1664,1145],[1097,842],[-1098,239],[267,1419],[1138,28],[-754,450],[-1016,-92],[202,803],[1422,335],[-93,974],[398,794],[-1113,257],[404,646],[1417,-864],[676,774],[-844,968],[2298,-86],[-857,1159],[219,774],[-1709,-12],[-1256,-416],[804,1357],[1301,206],[83,379],[-1258,123],[-1558,-249],[346,754],[-882,-173],[-847,-912],[-423,763],[-862,-156],[381,863]],[[576521,383405],[33,-1443],[2694,35],[40,-1457],[-2702,-36],[119,-4690],[171,-10538],[-2401,214],[-9646,-36]],[[564829,365454],[-12277,-70],[-2162,-145],[-31696,67],[-38438,-399],[-15149,-82],[-5289,172],[-9177,-57]],[[450641,364940],[-327,15268],[608,2701],[-4022,50],[-10029,-130]],[[111495,370782],[1932,-1362],[-357,-447],[-2057,-758],[-173,-991],[303,-857],[1402,-1678],[-86,-337],[-2417,-1267],[-876,309],[-1006,1210],[-1968,866],[-1203,38],[-1481,-501],[-1524,-814],[-3987,-1815],[-197,-542],[1377,-1570],[805,-200],[2051,708],[1054,-214],[1564,-1396],[2012,-2420],[896,-152],[3945,2131],[1455,922],[1254,-277],[2177,-1481],[51,-1186],[-852,-456],[-2587,584],[-1239,67],[-1434,-451],[-1934,-1712],[-2046,-681],[-1767,-143],[-2238,64],[-2632,-702],[-2600,163],[-1319,-537],[-551,-1338],[-672,-2593],[-1101,-2047],[-697,-1829],[-903,-1164],[-973,-447],[-1576,-287],[-1490,-894],[-640,-755],[-349,-2034],[-834,-666],[-1660,-2202],[-2473,-1106],[-287,-932],[535,-1316],[1391,-1755],[1870,-1912],[635,-1192],[147,-1742],[713,-1852],[3100,-2345],[2879,-1492],[1237,249],[772,829],[4391,1162],[2622,47],[1128,-586],[1307,-2384],[1450,-1918],[314,-778],[158,-4220],[1118,-3264]],[[107354,310134],[-10228,-115],[-15408,-31],[-38815,-33],[-15224,-54],[-7293,22],[-1470,-64],[-7235,40],[-9226,-67]],[[2455,309832],[-191,5098],[-917,12832],[-743,13750],[-439,5242],[-165,3943],[480,3349],[1359,8220],[1822,10563],[1142,7029],[2244,12858],[2495,15121],[2358,13812],[670,3602],[1870,11936]],[[854340,403404],[56,-1501],[-4853,-20],[-69,-4288],[-465,-6688],[-266,-7242],[415,-3603],[95,-4117],[-9502,-123],[-138,1667],[-2259,-21],[139,-1688],[-8174,61],[-3540,-96],[78,-2979],[-4817,-36],[-1455,-923],[-919,615],[-10924,-212],[-2543,53],[-1182,-354],[-817,-602],[329,-974],[-406,-1156],[-813,-1124],[-1549,-806],[-481,-620],[-210,-1960],[-1995,-1546],[-990,-1100],[-1788,-1026],[-924,-1184],[-1761,-1239],[-915,-1223],[-1626,-1159],[83,-994],[-1146,-1014],[-1198,-367],[-7,-1037],[-1042,-1089],[225,-711],[-194,-1282],[-1015,-572],[-451,-1259]],[[785326,347865],[-27775,39],[-9426,-21],[-1,9110],[278,9008],[-9399,-21],[-16903,21],[28,3044],[-1332,-18],[6,1498],[-1018,21],[-278,12154],[-4965,0],[-84,1544],[-9631,-38],[-7,1520],[-2300,-24],[28,-750],[1211,3],[-41,-753],[-7157,-27],[0,-666],[-2271,-36],[0,-752],[-2370,0],[0,731],[-1199,21]],[[450641,364940],[-4853,-110],[-9471,7],[138,-6263],[-50,-2868],[424,-12121],[-69,-3117],[92,-2952]],[[436852,337516],[-5213,5],[-13706,-123],[-17496,-87],[-23987,-171],[-394,-108],[-24851,39],[-3960,608],[-4538,79],[-1517,-90],[-9365,-10],[-25501,-164],[-4313,-111],[-11823,-119],[-9464,-35],[-4666,66],[-4896,-73]],[[271162,337222],[-16145,-359],[-17063,-79],[-235,9021],[-3369,1177],[-9428,-61],[-261,24105]],[[953150,385976],[-345,-2682],[94,-1448],[416,-906],[-356,-1697],[1312,-1395],[-664,-2157],[-575,-693],[-1365,-606],[-1681,-2491],[-334,-1979],[-643,-1064],[1367,-2043],[-530,-792],[-1700,-668],[-2595,-355],[-864,-520],[1087,-3044],[1033,-938],[-1674,-731],[-1813,-1667],[-1953,-647],[-558,-458],[-613,-1397],[-2874,-1084],[0,-480],[1311,-980],[-975,-333],[250,-1398],[-697,-624],[-1087,-210],[-4296,21],[-446,-584],[1311,-1604],[199,-1150],[-1426,-1436],[-587,-1585],[-1339,-1208],[809,-1397],[-167,-1211],[-975,-895],[725,-1189],[2036,-1480],[-719,-463],[914,-1997],[-475,-1502],[168,-2898],[-2656,-2478],[871,-836],[3151,-1772],[614,-563],[-557,-913]],[[933279,323349],[-2008,1058],[-1311,291],[-443,-435],[-966,846],[-1969,675],[-2353,-648],[-584,-629],[119,-659],[-1026,-547],[-100,-512],[-1035,209],[-1909,-1534],[-1878,-119],[-1576,-1384],[-945,217],[-2307,-952],[-1421,-71],[-1574,-3448],[-188,-1907],[635,-1074],[-1943,-1945],[-9443,303],[-17045,254],[-2395,131],[-4049,48],[-3437,-70],[-2050,110],[-5219,-13],[-12125,124],[41,-5216],[-159,-3434],[127,-2722],[-132,-6809]],[[852611,293487],[-14114,229],[-9175,-61],[-14366,-398],[-9482,-167],[-29500,72],[-5108,46],[-10805,-16]],[[760061,293192],[1652,273],[1837,1095],[1662,1621],[-262,863],[501,54],[811,1767],[1635,910],[888,1132],[193,1152],[-726,730],[812,928],[-465,2245],[453,1752],[-1009,1014],[260,811],[1531,322],[327,1232],[1651,697],[-281,879],[92,1362],[-351,396],[1329,910],[-681,687],[433,582],[686,2199],[1712,1434],[636,29],[2374,1190],[58,411],[1377,104],[2341,1012],[1404,2406],[-613,459],[403,1075],[1256,1107],[-1265,865],[29,817],[-920,253],[-218,1404],[-884,1219],[412,424],[80,1993],[-613,282],[933,1637],[433,2595],[-793,1174],[-1206,684],[-353,1433],[964,416],[2894,2544],[468,1005],[1378,1088]],[[760061,293192],[-11406,-17]],[[748655,293175],[-22123,105],[-15762,101],[-20914,73],[-1142,-49],[-14437,-54],[-18976,-134],[-6170,-87]],[[649131,293130],[-4748,-40],[-4661,-239],[-45,1824],[282,602],[1113,742],[828,111],[366,1053],[837,718],[1636,202],[410,1404],[545,613],[-792,620],[1329,1299],[2568,550],[72,2353],[-89,3885],[-56,8632],[122,4839],[-101,3831],[-280,3113],[-14237,-104],[-7,3629],[1816,877],[-197,1431],[1503,1064],[1442,1812],[-869,1262],[690,1462],[-207,1034],[398,1397],[45,1425],[681,260],[-411,842],[771,1319],[621,1614],[-171,555],[823,363],[404,1061],[-259,1246],[-548,588],[201,979],[60,2442],[-748,1284],[614,1415],[-1147,922],[144,549],[-863,1448],[127,808],[-1124,2710],[-1558,897]],[[649131,293130],[560,-16697],[-3575,-30],[57,-1526],[-10661,-53],[149,-7146],[81,-11602]],[[635742,256076],[-4669,349],[-14274,-113],[469,3034],[-4696,-26],[-191,9093],[-140,3274],[-541,2837],[-5202,-9],[-5,-1047],[-5478,-2516],[-337,-1323],[-2463,-792],[-596,20],[-60,-717],[-2037,-2083],[-955,-95],[-1111,602],[-538,-372],[240,-632],[-2157,130],[-1440,339],[-866,-372],[-647,-1083],[-2159,-1670],[-1153,-85],[-283,-426],[673,-482],[-1711,-716],[-1282,-1358],[-1475,-502],[-1082,-984],[-898,236],[-283,10116],[-105,5531],[-4308,-324],[-23382,-49]],[[550600,273861],[-40,5963],[-1225,24],[-56,3055],[1311,-47],[-79,18091],[14195,78],[67,5930],[675,3557],[66,3376],[-141,8777],[1218,-10],[-18,3095],[-1211,-6],[-36,11987],[1152,3],[-5,804],[1106,0],[-6,1522],[-1028,18],[-204,727],[-1073,3],[-216,3829],[-82,18337],[-141,2480]],[[271162,337222],[28,-3143],[-4855,49],[503,-17339],[118,-6964],[-14144,-148],[213,-15002],[90,-12953],[95,-1973],[-3576,-1574],[-1850,-1080],[-4173,-2873],[-4248,-1050],[-1184,-460],[-634,-1280],[477,-448],[2981,-1800],[3084,-1358],[2994,-801],[5719,-2061],[1394,-1579],[-322,-2009],[-1189,-2275],[-879,-2743],[-640,-1017],[-1125,-935],[-3397,-1811],[-1979,-2021],[-805,-427],[-2378,-736],[-1783,-30],[-1614,300],[-2416,1085],[-2841,1925],[-1327,547],[-4044,-221],[-2659,-668],[-1284,-612],[-4161,-2559],[-909,-292],[-3071,-382],[-1385,-575],[-821,-1017],[-1576,-2489],[-2996,-2042],[-3,-1371],[969,-1687],[-11,-2185],[-251,-1222],[-956,-948],[-1406,-607],[-2606,-618],[-1762,124],[-1577,851],[-275,1016],[485,2947],[-1127,1433],[-1997,216],[-538,-314],[-293,-1537],[244,-1541],[-1238,-1195],[-3548,-2068],[-442,-528],[-206,-1249],[477,-2532],[1217,-1291],[975,-536],[2051,-666],[724,-532]],[[197499,226341],[-154,-450],[-1640,-321],[-2340,834],[-2375,-66],[-1074,517],[-1424,1132],[-513,2390],[-1182,465],[-1495,-779],[-264,-997],[237,-802],[1719,-1094],[2024,-1891],[306,-941],[2394,-956],[658,-616],[-406,-872],[-2457,-1050],[-2720,45],[-3765,1471],[-1041,242],[-1650,-279],[-577,-916],[-846,-2587],[-1182,-804],[-1591,-464],[-74,-550],[1349,-1022],[-56,-418],[-1969,-1129],[129,-877],[2329,-1101],[-172,-650],[-948,-461],[-1292,373],[-488,975],[-1243,885],[-1540,215],[-1666,-725],[-634,-1334],[747,-1199],[1272,-1282],[1916,-788],[410,-946],[-1387,-793],[-1064,60],[-1331,546],[-1437,1579],[-1467,450],[-834,-375],[0,-922],[632,-1087],[-929,-1283],[-696,-81],[-1838,708],[-48,838],[-1020,-222],[-2819,-1466],[-472,309],[-1440,-18],[-1344,-1595],[-1153,-228],[355,-674],[-1123,-235],[-2072,106],[-2213,807],[-1924,-48],[-1695,662]],[[146892,204556],[-1089,1933],[316,824],[2443,1146],[163,1373],[2593,1807],[-1473,1028],[-2708,2913],[-912,285],[-2218,121],[-1316,308],[-996,581],[-808,1070],[-726,434],[-1617,-45],[-1162,-675],[-1333,-85],[-504,869],[1867,1006],[1526,1234],[2512,258],[1953,-841],[909,3],[821,587],[-131,560],[-1135,1404],[461,976],[1874,741],[582,1259],[-770,1041],[-1734,332],[-2040,1426],[-440,735],[792,983],[1272,248],[1606,-351],[2076,73],[1214,-198],[1680,-1039],[1658,42],[1014,787],[-22,2002],[693,858],[-389,1417],[301,1010],[709,355],[1423,-182],[1143,-720],[-119,-889],[-1690,-881],[456,-920],[1352,-245],[1272,708],[6,1579],[682,778],[1756,1064],[111,1758],[1010,1365],[953,634],[235,827],[-1103,1736],[1187,2248],[354,1891],[-1069,808],[-635,-449],[1016,-988],[-262,-995],[-2031,-693],[-1033,1201],[-2532,855],[-2199,-274],[-709,-482],[27,-613],[1059,-1595],[-865,-154],[-1578,808],[-1134,-94],[-3080,-963],[-872,77],[-339,686],[2722,1082],[491,591],[99,1143],[511,543],[1463,299],[4292,-260],[1708,735],[-12,1061],[-628,560],[-2812,468],[-1130,-658],[-1485,-7],[-275,584],[1769,1725],[1694,663],[1234,825],[-1335,1153],[-725,1067],[-1010,502],[-2965,107],[-731,408],[-22,765],[1895,555],[2689,302],[961,686],[-271,1673],[-816,1939],[1515,1734],[1417,1923],[785,1480],[-793,1002],[-460,-97],[-2931,983],[-1474,738],[-1067,1927],[-1223,1295],[-2112,1332],[-1084,269],[-5490,453],[-2585,508],[-1251,1172],[-4200,831],[-3563,1559],[-3031,583],[-3437,1579],[-1816,1939],[-885,690],[95,464],[1996,17],[2568,-765],[1344,220],[211,948],[-1192,1122],[-1574,490],[-2666,-172],[-3960,18],[-2911,970],[-2740,1223],[-2226,1672],[45,970],[1027,867],[405,1189],[-1664,1534],[-1136,1455],[-594,1794],[66,1128],[-392,1126],[-989,1315],[475,448],[1836,86],[1168,675],[50,1944],[-835,1543],[-907,681],[-793,1225],[-175,2299]],[[550600,273861],[-1949,-102],[-19104,-173],[-14024,-54],[-14077,-15],[-7304,54]],[[494142,273571],[-1699,-30],[-14446,84],[-5303,-106],[-7092,40],[-4665,315],[-5205,-24],[-188,868],[-976,1295],[-1985,11],[-2195,1338],[-1313,363],[-612,530],[-493,1315],[307,618],[-1194,2526],[-798,-249],[-308,2118],[-2133,1252],[396,745],[-1126,961],[-1057,1325],[-1681,3053],[-1640,1858],[-1813,2463],[-123,10772],[489,2469],[65,6586],[-190,5266]],[[437164,321333],[-161,6723],[-31,4806],[-120,4654]],[[437164,321333],[-1716,-150],[-1511,-632],[-1303,-67],[-3515,-702],[-785,-421],[-2633,-850],[-515,-974],[-1175,9],[-702,-530],[-1415,-363],[-1914,-54],[-3387,-850],[-825,-886],[-1891,-783],[-1703,226],[-2504,-929],[-2197,-296],[-1974,161],[-1219,-309],[-1232,78],[-4533,708],[-1091,545],[-793,-142],[-1361,-1703],[-1421,-1180],[-149,-2421],[784,-1501],[17,-625],[735,-1093],[-2292,-1566],[-2315,-204],[-1017,-298],[-1152,-830],[-749,-992],[-1776,-1303],[-4482,-221],[-2168,-467],[-2741,-1230],[-1557,101],[-2009,-525],[-1027,-3828],[611,-2241],[-837,-823],[-113,-1304],[-1106,-3056],[-1913,-1439],[-815,-899],[-1277,-2306],[-456,-1463],[322,-1964],[-1627,-1285],[-679,-1880],[787,-2468],[-4351,-4425],[-1738,-2346],[-1805,-932],[-1041,-1036],[88,-1440],[-1614,-1486],[-743,-1252],[-827,-497],[-3586,-326],[-2420,-434],[-1308,-1248],[-1175,-585],[-1420,-1310],[-3152,-1920],[-3421,-1676],[-821,-635],[-1007,-1513],[-3102,-621],[-3071,-1363],[-1862,-1810],[-932,-544],[-1372,-1653],[-1951,-837],[-2100,-3001],[-1848,-1806],[-1727,-757],[-1506,58],[-639,-263],[-313,-1801],[-543,-828],[-1852,-1767],[-1079,-2510],[-2352,-458],[-4415,-1941],[-1512,-930],[-1378,-293],[-1846,-1237],[-663,-950],[-3239,-1797],[-752,-242],[-1058,-941],[-1406,-1903],[-302,-1232]],[[291687,218620],[-17220,-66],[-238,-545],[-2713,-1128],[-2087,-660],[-3233,-416],[-1964,35],[-1057,-907],[-1035,-206],[-723,-931],[-2448,-815],[-1176,-692],[-1406,-106],[-1377,-476],[-602,376],[-2619,327],[-683,329],[-1844,269],[-2172,1090],[-1251,272],[-2871,272],[-216,306],[-2678,-175],[-930,526]],[[239144,215299],[-1273,84],[-1353,-309],[-1800,-48],[-1994,340],[-2262,949],[-3801,538],[-759,726],[-3297,1178],[-3508,2852],[-813,1715],[-3418,754],[-1065,1900],[-2057,1328],[-1080,266],[-1763,-622],[-1421,48],[-307,387],[-3893,-151],[-1197,-938],[-1442,6],[-501,396],[-1286,12],[-1355,-369]],[[933279,323349],[-502,-1047],[1952,-2837],[837,-2272],[-893,-1396],[56,-626],[-1143,-1106],[-195,-1792],[333,-1752],[-55,-1083],[1200,-1085],[2370,-1021],[865,-1585],[4769,-3732],[1395,-521],[2064,-396],[614,-980],[-1228,-209],[-1226,-1939],[223,-500],[1925,-501],[1478,-1314],[1701,-895],[2394,-627],[697,-1070],[-830,-1861],[971,-254],[230,-1137],[-440,-1041],[-239,-2527],[910,-1369],[-735,-1586],[1498,-1806],[459,-1264],[2428,-2200],[258,-783],[-390,-1159],[-1473,-1730],[87,-742],[899,-689],[-77,-418],[-2915,-3292],[-1424,-1960],[-477,-1153],[-938,-752],[-1776,-3404],[690,-1833],[21,-1359],[554,-862],[430,-1558],[-55,-2260],[-1205,-759],[-818,399],[-755,-737],[-174,-1683],[-973,-1203],[744,-1780],[-129,-952],[-727,-824],[-386,-1639],[-940,-1262],[-511,-1347],[-1500,-2153],[-33,-1413],[1794,-641],[-302,-2892],[-533,-978],[1249,-1195],[277,-926],[-109,-1576],[-1227,-1814]],[[944318,228689],[-6314,-106],[-19201,-103],[-8114,229],[-20117,419],[-11340,393],[-15041,396],[-11857,96]],[[852334,230013],[-24,4229],[161,2632],[113,5673],[-266,6729],[-152,6954],[753,12413],[0,6680],[-191,5950],[-117,12214]],[[494142,273571],[84,-4434],[-28,-6566],[62,-7208],[7350,-25],[980,-529],[-894,-880],[511,-1139],[1645,-684],[126,-967],[-752,-502],[1939,-2320],[-730,-618],[-693,-1690],[-638,280],[-1759,-1528],[1506,-679],[790,-1859],[97,-874],[-2051,-1457],[-1485,-655],[-453,-980],[-1944,-1010],[-1341,-472],[-1518,69],[-1140,-501],[881,-909],[-550,-735],[140,-2741],[39,-15471],[230,-8188],[-35,-3849]],[[494511,204450],[-1599,527],[-579,-923],[-3308,170],[-410,-209],[1304,-735],[-737,-488],[-2157,429],[-2229,-193],[-395,167],[-516,1709],[-1005,206],[-1722,-666],[-2029,215],[-1346,-1044],[-903,-1519],[-1010,497],[1212,635],[211,950],[-974,388],[707,725],[-1576,184],[-912,1214],[1740,696],[-43,402],[-1799,412],[112,383],[1779,1154],[544,659],[-274,645],[-1219,1071],[-138,2136],[-885,971],[426,592],[-349,747],[1460,702],[829,1549],[-22068,148],[-25497,-54],[-3278,-57],[-14952,-89],[-10155,58],[-1621,-36],[-14954,-21],[-8365,-42],[-32188,-41],[-2449,-29],[-21397,30],[-28110,-55]],[[146892,204556],[389,-2070],[-499,-1439],[465,-1062],[1044,-847],[48,-871],[-872,-348],[-2616,167],[-1527,-312],[-2514,508],[-1254,-36]],[[139556,198246],[-294,396],[-4150,1821],[-8935,-5732],[-677,-322],[-11014,-67],[-16563,47],[-9672,-49],[-9479,25],[-30812,-83],[-7951,34],[-108,-3888],[68,-2256],[-4769,63],[-7945,-115],[-15758,40]],[[11497,188160],[-416,6117],[-242,2338],[-140,3748],[-557,6928],[-762,11562],[-1500,18951],[-333,3702],[-913,13698],[-447,4920],[-149,4604],[-401,3885],[-99,2339],[-518,6512],[-1086,15239],[-355,3234],[-303,4114],[-821,9781]],[[852334,230013],[-80,-2958],[182,-3056],[-19071,190],[-111,-4049],[-5,-4499],[-1284,-88],[-2035,275],[-2024,-63],[-933,654],[-2701,529],[-4144,-45],[-4016,523],[-1629,465],[-3376,1334],[-1341,-187],[-1583,445],[-2746,-70],[-1100,572],[-3891,1162],[-1332,-195],[-388,343],[-1540,-118],[-2072,317],[-2668,-178],[-892,468],[-2545,-694],[-544,211],[-3793,-488],[-1614,-680],[-1288,-1634],[-1315,-883],[1113,-1126],[-2126,-2350],[-1230,-362],[-1042,184],[-747,-981],[467,-1055],[-533,-1470],[-1099,-258],[699,-1279],[-289,-688],[-1382,-880],[163,-339],[-1085,-665],[-1354,182],[-204,-975],[-894,154],[-861,-330],[438,-355]],[[770489,205023],[-22483,250]],[[748006,205273],[65,6047],[-96,6051],[167,7766],[-29,1434],[322,7887],[95,7590],[-180,8782],[-28,6024],[333,11759],[0,24562]],[[748006,205273],[-23450,0],[-13799,-48],[-3703,42],[-6148,-81],[-9228,-31],[-12505,-236],[-14719,-315],[-7171,-32],[-2,-2276],[-2418,-9],[-20,2232],[-18963,-114]],[[635880,204405],[-141,3818],[53,4907],[123,3360],[-605,27156],[-239,9384],[671,3046]],[[635880,204405],[143,-2732],[-76,-11312],[77,-1188],[510,-16600],[73,-4628],[151,-2965],[944,-9],[-88,-1888]],[[637614,163083],[-11168,19],[-3082,54],[-5027,-107],[-9426,-35],[-7615,103],[-15862,60],[-3994,-61],[-4335,45],[-14091,-126],[-3264,24],[-9366,-118],[-8139,67],[-10571,338],[-2005,-66],[-16498,-12],[-8855,-79],[-6462,-4]],[[497854,163185],[71,1181],[-3391,51],[-32,12672],[-114,12792],[123,14569]],[[256484,12631],[105,887],[2375,657],[2171,-76],[2309,172],[2886,753],[13,-925],[-2977,-230],[-6882,-1238]],[[259863,14667],[2762,494],[1695,613],[2340,433],[592,396],[2407,569],[590,478],[1800,324],[2181,-142],[4636,1501],[4520,339],[-519,-748],[-773,-30],[-2246,-641],[-2811,-525],[-1501,-671],[-4071,-777],[-2976,-453],[-2600,-603],[-1441,-72],[-3793,-681],[-792,196]],[[144836,94177],[257,660],[1674,2102],[615,336],[152,1041],[781,1218],[584,327],[1040,1392],[1466,-2463],[54,-1125],[726,-2236],[292,-1624],[-836,-2269],[-2010,1452],[1108,862],[-678,1125],[-1867,309],[-503,432],[-1006,-226],[-1143,-1059],[-706,-254]],[[130994,97795],[2005,1419],[3580,3340],[1456,2976],[1204,1522],[15,409],[1407,1437],[1776,1186],[1640,565],[2923,460],[2980,-271],[-1378,-2342],[-330,-1676],[71,-2560],[609,-1410],[-360,-928],[-1470,-1806],[-550,-1007],[-152,-1126],[-1992,-2082],[-1562,-138],[-916,429],[22,1068],[1157,0],[-508,1651],[-755,137],[-154,717],[1235,525],[-506,1541],[-941,731],[1484,945],[-797,406],[-1193,-26],[-1374,-704],[-905,243],[-688,-352],[-325,-838],[-1774,-1757],[-722,-1731],[-1449,-405],[-506,-623],[687,-514],[-1266,-53],[-1678,642]],[[239144,215299],[-30,-15686],[105,-9188],[-139,-2308],[172,-3094],[5,-4013],[-123,-2308],[81,-2414],[44,-12509],[4632,20]],[[243891,163799],[590,-2056],[926,-966],[-215,-1124],[312,-960],[1089,-1945],[-691,-1452],[-97,-1062],[-1767,-2665],[-853,-523],[-1794,-2469],[-667,-1628],[-475,-435],[-1165,-2729],[-1711,-826],[-89,-804],[445,-773],[-215,-870],[-757,-215],[-1408,-960],[-1527,-2969],[1860,-1199],[845,-1204],[-585,-1343],[3104,-1878],[149,-927],[3068,-626],[376,-363],[706,-1800],[1854,-989],[1742,-269],[1681,-551],[1400,-884],[1343,-1594],[1920,-801],[2435,-1740],[1526,-819],[1678,-1262],[-223,-1419],[1442,-1419],[1131,-704],[308,-2406],[1626,-1477],[-112,-383],[1065,-130],[3262,-1453],[992,-69],[1611,-1392],[791,-980],[1332,-311],[2915,-342],[1626,-405],[458,-772],[1435,-1295],[1130,-281],[1120,-927],[1207,-138],[851,-521],[2115,445],[2754,-1585],[596,-584],[2511,-160],[2316,-1519],[3233,-883],[1073,-482],[231,-1703],[1434,-1978],[763,-372],[502,-1028],[-287,-487],[821,-1332],[-399,-1884],[547,-482],[-754,-2801],[393,-343],[-1232,-2174],[-389,161],[-1851,-870],[215,-1034],[-568,-2674],[-629,-680],[49,-888],[-617,-1030],[-899,223],[-665,-2181],[-2069,-363],[-412,-1128],[-1094,-917],[-1108,-245],[-427,-1282],[-1341,-1247],[627,-1286],[-1373,130],[-597,-908],[361,-430],[-332,-1121],[423,-978],[-1237,-97],[616,-949],[906,-567],[1009,-63],[2420,-2014],[-85,-892],[934,-634],[-256,-558],[-1266,62],[322,-668],[-1284,15],[49,-529],[1290,-1930],[2081,-1879],[1873,-904],[-327,-273],[1501,-1231],[2608,-309],[725,-617],[3385,-287],[-1663,-1253],[-562,-1061],[-179,-1673],[-500,-736],[-912,-35],[-1827,-971],[-2441,101],[-3224,-435],[-1285,-1237],[-497,-1325],[-2569,-832],[-977,-484],[-63,-1008],[-816,-1427],[462,-1087],[-1474,-882],[-1232,-1296],[171,-521],[-731,-1388],[-2593,-1458],[-3782,-2493],[-1157,124],[-95,1247],[-1292,492],[-45,1287],[340,490],[-951,949],[565,879],[-702,120],[-701,-729],[588,-829],[-384,-1050],[657,-287],[-296,-1101],[1247,-339],[-1057,-1008],[-2192,-892],[50,511],[-1187,971],[39,1198],[-972,872],[-43,-1851],[-2373,-805],[-633,-581],[790,-40],[1854,706],[971,-176],[210,-548],[-1086,-1615],[-1052,-2636],[-859,179],[-2779,24],[-713,225],[-989,-1673],[-518,-442],[-310,-1162],[-1063,34],[-1893,671],[-1132,1791],[-275,-1325],[-601,-385],[-1765,617],[-1274,-160],[-1021,-1262],[-1133,-925],[-1477,2093],[-732,1398],[133,1755],[877,962],[791,279],[55,1115],[-613,443],[532,1258],[819,593],[-1701,-194],[-110,-946],[-1064,-1535],[-1616,-571],[-769,94],[38,1182],[-1685,729],[297,741],[-359,1069],[342,486],[-1472,473],[-30,853],[-618,-1220],[-1399,139],[-855,-801],[2018,-60],[812,-297],[407,-859],[-413,-742],[-1085,-496],[1417,-968],[-839,-267],[181,-1034],[1977,-1479],[1334,-215],[-2345,-2843],[-1070,-482],[-677,146],[-805,-687],[-1666,-166],[-935,510],[148,-1073],[2768,76],[4684,-729],[1799,-482],[1850,-45],[2085,345],[1671,1398],[1067,266],[3005,-578],[-384,-520],[1334,-201],[2051,1042],[1699,185],[3010,1630],[1825,-128],[819,-341],[-193,-1576],[-3734,-527],[-1687,-523],[-1867,-1180],[-1354,539],[-2564,-233],[-2127,-826],[362,-538],[1421,-376],[-476,-505],[-2734,-439],[-1726,-608],[728,-193],[1973,172],[789,354],[1395,-97],[-663,-1140],[-1630,-354],[-2904,27],[-3503,-608],[-3008,-657],[-9717,-1863],[-1942,-257],[-4681,-953],[-4415,-164],[-4140,-305],[-3834,-581],[-5382,-441],[-4177,-174],[-845,-253],[-11836,-1670],[-5035,-617],[-5725,-328],[-4994,-144],[-5602,151],[-4362,37],[-10635,414],[-5212,72],[-8717,-187],[-10528,-787],[-2725,-469],[-4248,37],[-1399,299],[1731,1083],[1620,285],[6531,208],[3097,321],[4109,87],[1951,868],[1120,-508],[1165,345],[297,730],[-1921,1056],[1298,756],[1340,6],[-97,766],[732,637],[1488,249],[1986,689],[3279,-1649],[1640,-141],[822,-948],[1480,-628],[4127,-1202],[2670,-175],[2705,9],[3416,196],[2573,515],[8274,2223],[1810,306],[4449,-251],[3887,242],[3080,672],[2732,994],[3229,3159],[124,874],[940,201],[1287,1240],[-203,807],[718,481],[1036,-454],[1508,-1719],[296,-1457],[-617,-297],[-502,-1132],[715,-1227],[887,-110],[2182,542],[1057,972],[-190,986],[-857,1177],[-2218,109],[-1557,2420],[1636,1382],[1001,66],[540,539],[-1530,42],[-2108,-864],[-2839,-258],[-1329,-1319],[-1005,499],[-2009,2093],[-1550,1389],[-7920,3202],[-2277,1206],[-6069,4604],[-971,1260],[-1024,1783],[180,1230],[1474,441],[72,1642],[1967,932],[1621,312],[826,-675],[222,1274],[-1847,745],[-49,1249],[-813,1138],[-396,1151],[-958,-571],[-61,756],[-1481,-457],[-881,-1373],[-1661,-1144],[-604,-882],[27,-972],[759,-741],[1593,-2414],[-4438,362],[-3303,1074],[-6388,3044],[-2554,1382],[-2167,745],[-1111,1240],[-1304,5476],[-136,1089],[-1110,2471],[-678,2933],[-1271,1058],[-1914,913],[-1415,375],[858,666],[1731,1979],[1731,3201],[1348,1249],[2123,2789],[56,488],[1788,2026],[179,1785],[-457,2475],[-705,1433],[-1559,1465],[-943,2045],[219,2592],[443,1928],[-45,1596],[-1260,1665],[-894,541],[611,1270],[-177,726],[748,857],[521,2495],[-579,536],[-944,-24],[-240,-1690],[-978,-1423],[-391,1482],[224,1145],[788,2069],[-327,1449],[462,1010],[-468,1936],[-1617,2054],[-839,1706],[-230,1673],[-1378,1238],[214,1600],[966,1256],[1239,2926],[1844,1436],[213,500],[-2052,-152],[-2138,-814],[-1032,208],[-879,-274],[-4032,-494],[-1561,-463],[-2059,-1587],[-1799,-1162],[-941,-1147],[-547,-1125],[-321,-1541],[-845,-1427],[-846,-508],[-414,847],[1568,2756],[-2301,805],[-665,-1111],[785,-698],[-354,-399],[-1510,-94],[-1192,641],[-1439,17],[-973,1453],[-135,1141],[264,1004],[705,901],[3351,1734],[-659,281],[283,591],[2270,1567],[1470,244],[461,1437],[-1455,338],[-469,-435],[-866,1410],[67,965],[-1390,119],[-1012,-621],[-3080,-835],[-538,-1053],[-1342,-1031],[0,-860],[766,-2032],[-425,-85]],[[126590,111167],[-1925,1346],[-13,391],[1709,2343],[-22,649]],[[126339,115896],[-653,468],[1620,1884],[2085,987],[2089,672]],[[131480,119907],[1394,353],[1231,618],[594,1074],[-442,1631],[272,829],[1191,620],[3178,750],[2685,1040],[1546,206],[2672,13],[1187,595],[625,992],[69,841],[-553,1368],[-1991,1748],[-1987,1135],[-3064,1062],[-2270,545],[-1709,1068],[-338,861],[61,1393],[1356,2193],[1659,1360],[2191,1329],[2340,901],[1172,1470],[252,2240],[1267,1056],[1566,398],[1461,76],[4040,1210],[-423,1543],[-882,874],[-2000,424],[-1587,1062],[-424,1446],[-737,645],[-1466,423],[-2891,-81],[-1075,269],[126,653],[1101,1232],[111,1388],[1076,1286],[-11,1159],[-462,1790],[-1465,448],[-289,617],[1648,944],[1172,-170],[1274,1538],[56,414],[-1657,1174],[-576,928],[492,920],[2220,907],[1231,738],[847,1256],[-223,2357],[-961,1132],[-953,262],[-4412,-35],[-1575,1809],[-1435,973],[-510,818],[213,989],[653,571],[1900,977],[4092,3807],[1476,1185],[719,1067],[60,1998],[1077,1285],[68,1129],[-1541,505],[-2481,-683],[-1281,-10],[-2329,469],[-1305,729],[-714,1144],[474,1059]],[[944318,228689],[231,-9],[-769,-3028],[-1116,-1222],[-2307,-1203],[-2253,-241],[-979,-1004],[624,-724],[-257,-1905],[297,-947],[764,-802],[1822,-3670],[1035,-1150],[474,-1055],[-513,-1858],[-19,-1582],[-2162,-1654],[-365,-1528],[-3,-1501],[2229,-1153],[386,-894],[-437,-760],[-372,-1878],[1272,-932],[3696,-315],[1781,-442],[2040,-1961],[1389,-895],[745,-1017],[482,-1508],[2028,-2639],[1239,-191],[1598,-1125],[1832,-644],[443,-1222],[1273,-1283],[1265,-3037],[-912,-1606],[2307,-2179],[719,-1156],[1422,-701],[1288,-2417],[-218,-2418],[1100,-1497],[275,-1407],[1426,-1155],[-143,-1036],[-859,-1666],[-15397,-21],[-276,36],[-24354,-12],[-5198,57],[-12708,-39],[-9372,21],[-8077,-146],[-27062,-305],[-33104,-345]],[[832568,163718],[443,7243],[293,9899],[73,8851],[-7,5515],[-127,10779],[-9937,-372],[-6479,-172],[-11436,-500],[-10843,-11],[-24059,73]],[[497854,163185],[-4510,32],[-5558,393],[-5773,-43],[-2834,76],[-20900,144],[-16880,73],[-9722,-15],[-20335,206],[-1635,136],[-14143,-45],[-17803,67],[-1700,-130],[-4404,153],[-14683,-268],[-8744,-224],[-3463,-158],[-4972,363],[-3221,-78],[-2716,109],[-9950,27],[-978,-121],[-5204,0],[-3844,87],[-3435,-91],[-15303,47],[-2941,-56],[-9161,31],[-330,81],[-16875,-154],[-8751,15],[-13195,-43]],[[832568,163718],[-23573,-172],[-28843,-127],[-20472,-72],[-739,-98],[-32949,-217],[-1174,-31],[-34589,-159],[-369,56],[-15608,54],[-1822,-111],[-16465,4],[-3145,90],[-9949,51],[-5257,97]],[[97585,6039],[501,-3],[1424,-2187],[3863,-1937],[4988,-1615],[125,-297],[-4202,1202],[-2074,874],[-2756,1374],[-1176,914],[-693,1675]],[[40409,3396],[246,342],[1933,499],[3055,-209],[8035,545],[2340,383],[2541,621],[1711,97],[3479,637],[9083,1107],[8111,715],[2855,341],[1733,-45],[4962,206],[2871,578],[2298,-738],[620,1312],[834,218],[734,-493],[2290,334],[-681,629],[414,620],[1955,-1453],[1674,-574],[1452,-52],[573,385],[965,-467],[-449,1148],[-2651,1245],[-632,578],[-2880,787],[-878,-578],[-668,290],[-300,1353],[-1140,484],[1124,290],[4848,-2311],[5804,-2985],[1772,-1218],[-541,-882],[-5774,-827],[-3435,315],[-3083,623],[-574,300],[-3277,239],[-8379,-1],[-6841,-455],[-4711,-457],[-8805,-1240],[-8459,-1380],[-4690,-615],[-3246,-220],[-8218,-21]],[[68502,22661],[1199,326],[1225,-107],[-704,-529],[-1720,310]],[[91288,23552],[772,424],[814,-137],[1379,1172],[1168,608],[-1439,-3091],[-322,-1792],[-632,184],[-1729,2079],[-11,553]],[[58254,25637],[952,169],[1057,1005],[-769,928],[-873,125],[1020,2647],[-97,1851],[568,-169],[512,-1032],[-153,-1930],[367,-1688],[764,-1294],[71,-1063],[-643,-2015],[-1245,218],[-1004,1863],[-527,385]],[[117329,61499],[1630,1155],[2144,2051],[2229,-257],[1201,-898],[428,-769],[429,-4039],[-86,-705],[-1629,449],[-3687,1603],[-2659,1410]],[[126590,111167],[591,-1653],[51,-2529],[425,-1197],[1072,-1685],[1629,-1380],[143,-783],[-722,-1380],[71,1812],[-434,702],[-1881,893],[-869,-2245],[-1446,-1081],[-180,-568],[3762,-1379],[-2136,-1650],[-398,-1406],[-973,-757],[-812,-83],[-1660,1635],[-460,2379],[180,1434],[-359,989],[-507,3395],[-787,1546],[-324,1405],[99,1348],[1025,2338],[2085,3346],[1438,1518],[1126,-235]],[[131480,119907],[-384,88],[-3363,-676],[-843,-446],[-3626,-3668],[-3013,-4129],[-566,-993],[86,-2889],[1198,-4162],[-243,-476],[558,-1112],[348,-1728],[-167,-3028],[165,-881],[645,-380],[523,-1026],[10,-1385],[-375,-1408],[-1229,-677],[-1085,-107],[-2895,703],[290,378],[1808,27],[861,620],[488,1328],[-930,-429],[-2859,-675],[-1456,-1319],[1111,-607],[-146,-513],[-1193,-244],[6,-947],[1096,-597],[209,-852],[-1085,-796],[-146,-1382],[1108,-1262],[428,-1089],[-1480,-2000],[-1441,-2680],[-3990,-2762],[-1282,-771],[-832,-992],[-1323,440],[229,1072],[-3260,1089],[-2228,2245],[-601,1218],[258,1665],[2228,1476],[1115,320],[1029,-320],[686,320],[-1372,449],[-3087,320],[-1886,-1923],[-258,-2500],[-1457,64],[257,-512],[-858,-1026],[2230,0],[1030,-706],[1628,-2307],[600,-1155],[944,450],[1287,128],[942,-769],[2102,-835],[719,-1182],[598,-2592],[-546,-2382],[16,-1140],[-1682,-614],[-2958,-2772],[-1107,-2235],[265,-2057],[1253,-2768],[349,-1441],[-1349,-2420],[-782,-393],[-511,-1268],[422,-4056],[386,-2278],[-305,-2130],[-598,-2713],[-103,-4161],[-476,-1300],[-1774,-3017],[-2801,-3309],[-865,-581],[-1343,1010],[420,727],[-1007,148],[-1529,-236],[-153,-1155],[-1316,-1532],[-1522,1074],[-1366,506],[-321,-437],[1051,-1481],[573,-294],[-1964,-808],[-2830,-233],[-1994,-399],[-4166,-1307],[-1177,759],[762,772],[-868,1640],[613,347],[-1240,1422],[752,384],[1120,-631],[532,423],[253,3095],[739,1283],[1313,-282],[-21,430],[-1866,580],[-1457,-528],[-2964,-328],[-1462,-496],[-2085,1536],[-3265,873],[-2144,168],[-2531,1017],[-3297,839],[-3280,-131],[-924,296],[-2117,160],[-2164,467],[-181,518],[-1220,184],[-2161,-539],[-967,-1225],[-3,-1132],[-702,-965],[-2093,-57],[-595,399],[1121,1104],[-154,1162],[-842,551],[353,1207],[-1828,1237],[-1374,327],[-2941,1165],[-1147,-94],[-1153,-502],[-2318,947],[-1917,-194],[-39,-1422],[-1260,-1924],[-771,-190],[473,1860],[-275,362],[-1134,-107],[-1425,-624],[-140,-708],[-1305,323],[-597,-540],[1231,-637],[-53,-943],[-1132,52],[11,583],[-878,793],[-2967,-472],[-1298,18597],[-255,4991],[-345,4103],[-1269,19530],[-40,3773],[-328,3705],[-886,15643],[-359,5368],[-1540,24256],[-260,1806],[-1300,19150],[-337,6523],[-870,11042],[-202,1909],[-761,11230]]]}
