{"type":"Topology","transform":{"scale":[0.000008511727261945483,0.000012992200492200479],"translate":[-165.82453365799995,-21.938897393999937]},"objects":{"provinces":{"type":"GeometryCollection","geometries":[{"type":"MultiPolygon","arcs":[[[0]],[[1]],[[2]],[[3]],[[4]],[[5]]],"properties":{"adm1_code":"COK+00?","iso_a2":"CK","name":"COK-00 (Cook Is. aggregation)"}}]},"countries":{"type":"GeometryCollection","geometries":[{"type":"MultiPolygon","arcs":[[[0]],[[1]],[[2]],[[3]],[[4]],[[5]]],"properties":{"name":"Cook Is.","postal":"CK","iso_a2":"CK"}}]}},"arcs":[[[922942,2048],[2850,2448],[6410,-2680],[-1014,-1415],[-6386,106],[-1860,1541]],[[702356,54268],[2682,3445],[9480,-963],[-58,-4059],[-12104,1577]],[[903381,151044],[6683,-1365],[-4322,-1653],[-2361,3018]],[[949560,164273],[4010,2882],[-29,-5700],[-3981,2818]],[[707520,236532],[3833,2424],[-798,-3376],[-3035,952]],[[918291,999523],[7936,-1666],[-4452,-113],[-3484,1779]]]}
