{"type":"Topology","transform":{"scale":[0.000009456738372245401,0.00000462478693329019],"translate":[20.242825968743432,43.650049948000174]},"objects":{"provinces":{"type":"GeometryCollection","geometries":[{"type":"Polygon","arcs":[[0,1,2,3,4]],"properties":{"adm1_code":"ROU-122","iso_a2":"RO","name":"Dolj","postal":"DJ"}},{"type":"Polygon","arcs":[[-5,5,6,7,8]],"properties":{"adm1_code":"ROU-123","iso_a2":"RO","name":"Gorj","postal":"GJ"}},{"type":"Polygon","arcs":[[-4,9,10,-6]],"properties":{"adm1_code":"ROU-124","iso_a2":"RO","name":"Mehedinti","postal":"MH"}},{"type":"Polygon","arcs":[[11,12,13,-2,14]],"properties":{"adm1_code":"ROU-126","iso_a2":"RO","name":"Olt","postal":"OT"}},{"type":"Polygon","arcs":[[15,16,-13,17,18]],"properties":{"adm1_code":"ROU-127","iso_a2":"RO","name":"Teleorman","postal":"TR"}},{"type":"Polygon","arcs":[[19,20,21,22,23]],"properties":{"adm1_code":"ROU-128","iso_a2":"RO","name":"Bucharest","postal":"BI"}},{"type":"Polygon","arcs":[[24,25,26,-21,27]],"properties":{"adm1_code":"ROU-129","iso_a2":"RO","name":"Calarasi","postal":"CL"}},{"type":"Polygon","arcs":[[-23,28,-19,29,30,31]],"properties":{"adm1_code":"ROU-130","iso_a2":"RO","name":"Dâmbovita","postal":"DB"}},{"type":"Polygon","arcs":[[-27,32,-16,-29,-22]],"properties":{"adm1_code":"ROU-131","iso_a2":"RO","name":"Giurgiu","postal":"GR"}},{"type":"Polygon","arcs":[[33,34,-28,-20,35,36]],"properties":{"adm1_code":"ROU-132","iso_a2":"RO","name":"Ialomita","postal":"IL"}},{"type":"Polygon","arcs":[[-25,-35,37,38,39]],"properties":{"adm1_code":"ROU-133","iso_a2":"RO","name":"Constanta","postal":"CT"}},{"type":"Polygon","arcs":[[40,41,42,43,44]],"properties":{"adm1_code":"ROU-276","iso_a2":"RO","name":"Arad","postal":"AR"}},{"type":"Polygon","arcs":[[45,46,47,-44,48,49]],"properties":{"adm1_code":"ROU-277","iso_a2":"RO","name":"Bihor","postal":"BH"}},{"type":"Polygon","arcs":[[-7,-11,50,51,52]],"properties":{"adm1_code":"ROU-278","iso_a2":"RO","name":"Caras-Severin","postal":"CS"}},{"type":"Polygon","arcs":[[-42,53,-52,54]],"properties":{"adm1_code":"ROU-280","iso_a2":"RO","name":"Timis","postal":"TM"}},{"type":"Polygon","arcs":[[55,56,57]],"properties":{"adm1_code":"ROU-287","iso_a2":"RO","name":"Botosani","postal":"BT"}},{"type":"Polygon","arcs":[[58,59,60,61,62,-45,-48]],"properties":{"adm1_code":"ROU-294","iso_a2":"RO","name":"Alba","postal":"AB"}},{"type":"Polygon","arcs":[[63,64,65,66]],"properties":{"adm1_code":"ROU-295","iso_a2":"RO","name":"Bistrita-Nasaud","postal":"BN"}},{"type":"Polygon","arcs":[[-66,67,-59,-47,68,69]],"properties":{"adm1_code":"ROU-296","iso_a2":"RO","name":"Cluj","postal":"CJ"}},{"type":"Polygon","arcs":[[70,-8,-53,-54,-41,-63]],"properties":{"adm1_code":"ROU-297","iso_a2":"RO","name":"Hunedoara","postal":"HD"}},{"type":"Polygon","arcs":[[71,-67,-70,72,73,74]],"properties":{"adm1_code":"ROU-298","iso_a2":"RO","name":"Maramures","postal":"MM"}},{"type":"Polygon","arcs":[[75,76,77,-60,-68,-65,78]],"properties":{"adm1_code":"ROU-299","iso_a2":"RO","name":"Mures","postal":"MS"}},{"type":"Polygon","arcs":[[-69,-46,79,-73]],"properties":{"adm1_code":"ROU-300","iso_a2":"RO","name":"Salaj","postal":"SJ"}},{"type":"Polygon","arcs":[[-74,-80,-50,80]],"properties":{"adm1_code":"ROU-301","iso_a2":"RO","name":"Satu Mare","postal":"SM"}},{"type":"Polygon","arcs":[[-30,-18,-12,81,82,83]],"properties":{"adm1_code":"ROU-302","iso_a2":"RO","name":"Arges","postal":"AG"}},{"type":"Polygon","arcs":[[84,-83,85,-61,-78]],"properties":{"adm1_code":"ROU-303","iso_a2":"RO","name":"Sibiu","postal":"SB"}},{"type":"Polygon","arcs":[[-82,-15,-1,-9,-71,-62,-86]],"properties":{"adm1_code":"ROU-304","iso_a2":"RO","name":"Vâlcea","postal":"VL"}},{"type":"Polygon","arcs":[[86,87,88,-31,-84,-85,-77,89]],"properties":{"adm1_code":"ROU-305","iso_a2":"RO","name":"Brasov","postal":"BV"}},{"type":"Polygon","arcs":[[90,91,92,-87,93]],"properties":{"adm1_code":"ROU-306","iso_a2":"RO","name":"Covasna","postal":"CV"}},{"type":"Polygon","arcs":[[94,95,-94,-90,-76,96]],"properties":{"adm1_code":"ROU-307","iso_a2":"RO","name":"Harghita","postal":"HR"}},{"type":"Polygon","arcs":[[97,98,99,-56,100]],"properties":{"adm1_code":"ROU-308","iso_a2":"RO","name":"Iasi","postal":"IS"}},{"type":"Polygon","arcs":[[-99,101,102,-95,103]],"properties":{"adm1_code":"ROU-309","iso_a2":"RO","name":"Neamt","postal":"NT"}},{"type":"Polygon","arcs":[[104,-36,-24,-32,-89]],"properties":{"adm1_code":"ROU-310","iso_a2":"RO","name":"Prahova","postal":"PH"}},{"type":"Polygon","arcs":[[-100,-104,-97,-79,-64,-72,105,-57]],"properties":{"adm1_code":"ROU-311","iso_a2":"RO","name":"Suceava","postal":"SV"}},{"type":"Polygon","arcs":[[106,107,-91,-96,-103]],"properties":{"adm1_code":"ROU-312","iso_a2":"RO","name":"Bacau","postal":"BC"}},{"type":"Polygon","arcs":[[-38,-34,108,109,110]],"properties":{"adm1_code":"ROU-313","iso_a2":"RO","name":"Braila","postal":"BR"}},{"type":"Polygon","arcs":[[-109,-37,-105,-88,-93,111]],"properties":{"adm1_code":"ROU-314","iso_a2":"RO","name":"Buzau","postal":"BZ"}},{"type":"Polygon","arcs":[[112,-39,-111,113,114]],"properties":{"adm1_code":"ROU-315","iso_a2":"RO","name":"Galati","postal":"GL"}},{"type":"Polygon","arcs":[[115,-115,116,-107,-102,-98]],"properties":{"adm1_code":"ROU-316","iso_a2":"RO","name":"Vaslui","postal":"VS"}},{"type":"Polygon","arcs":[[-114,-110,-112,-92,-108,-117]],"properties":{"adm1_code":"ROU-317","iso_a2":"RO","name":"Vrancea","postal":"VN"}}]},"countries":{"type":"GeometryCollection","geometries":[{"type":"Polygon","arcs":[[39,25,32,16,13,2,9,50,54,42,48,80,74,105,57,100,115,112]],"properties":{"name":"Romania","postal":"RO","iso_a2":"RO"}}]}},"arcs":[[[373565,231900],[2197,-10290],[8960,-9119],[2181,-10687],[5973,-11610]],[[392876,190194],[-5546,-13883],[10388,-15722],[3628,-1967],[8793,-15990],[4022,-9871],[9666,-9627],[476,-18229],[2212,-5823],[-6333,-2475],[-1213,-11027],[8644,-6270],[182,-7546],[-3001,-2789],[1262,-10637],[-7153,-17465],[-5782,-18241]],[[413121,22632],[-36977,13782],[-8373,5917],[-8949,-2956],[-4591,1141],[-11421,9336],[-16871,1295],[-9589,-2010],[-10852,-6347],[-22447,-2967],[-5935,4581],[-1366,8989],[3737,21092],[14503,8022],[1803,6638],[-3358,8243]],[[292435,97388],[8703,13371],[5169,1844],[-835,14074],[5360,25152],[9683,4771],[-5957,5263],[148,11441],[4530,3297],[5105,9286],[18966,8771]],[[343307,194658],[9716,10057],[16438,7044],[-132,21572],[4236,-1431]],[[343307,194658],[-8749,16095],[-9283,8532],[-18345,7666],[-12551,15061],[-9439,15638],[-2623,19091],[542,9314],[-7667,10597],[-12912,3867],[-4530,8548],[-4148,2804]],[[253602,311871],[-688,7598],[-7241,2448],[694,6900],[10203,15073]],[[256570,343890],[22447,11777],[15394,-7626],[6743,4257],[10438,-1642],[5775,5061],[11994,5693],[7712,-3827],[16425,10548]],[[353498,368131],[15044,-4246],[6464,1067],[4925,-6755],[-1557,-12604],[2359,-12810],[-2262,-13017],[296,-10241],[-4858,-28823],[1574,-24845],[-1918,-23957]],[[292435,97388],[-10773,4851],[-22808,22919],[-974,16525],[-10437,4994],[-8218,16360],[-2972,12950],[754,7744],[7672,4693],[939,7340],[5881,2984],[8349,-5923],[4394,2168],[2481,6694],[-6875,10336],[-8349,1474],[-7181,6860],[-7356,11856],[-6098,2090],[-4798,-7162],[-6448,-3286],[-14229,-36807],[-8546,-1184],[-7410,18711]],[[189433,204575],[12235,329],[2015,2437],[-393,20162],[5989,22477],[4301,469],[5137,-6588],[4547,-33],[3556,-5202],[5710,3409],[5286,24906],[4430,10732],[3482,19392],[7874,14806]],[[443598,259467],[3792,-5912],[9514,14862],[638,-9397],[5498,-17186],[3333,-5386],[6825,-436],[-2676,-9883],[3431,-9682],[2759,-22750],[-760,-7967],[2285,-20013],[9088,-5736]],[[487325,159981],[-1509,-10628],[1198,-19772],[-1510,-12111],[754,-16772],[-6956,-4962],[-4382,-6340],[-8071,-4051],[-2759,-11626],[12010,-39751],[-8821,-11134]],[[467279,22834],[-17091,9480],[-7290,-1150],[-7716,-7386],[-22061,-1146]],[[392876,190194],[6530,4598],[5891,-7285],[7831,10631],[7087,-430],[8103,11566],[4219,-7509],[-4955,35186],[5218,11956],[1869,12771],[5726,11510],[3416,-3660],[-213,-10061]],[[557357,185049],[2426,-5877],[-4541,-15588],[5973,-16671],[10842,-2549],[6012,-7664],[1049,-26477],[-3990,-2296],[-4152,-16291],[645,-18661],[2720,-22493],[4400,-13452],[1809,-22170]],[[580550,14860],[-6510,-307],[-12142,-10162],[-9425,-564],[-6799,-3827],[-4601,916],[-11343,10889],[-18055,3089],[-12470,6631],[-22318,-2334],[-9608,3643]],[[487325,159981],[4530,1680],[9208,-1429],[4311,5485],[8405,1419],[9365,6583],[9355,-3498]],[[532499,170221],[7350,2610],[4826,10161],[230,6834],[12452,-4777]],[[637304,239957],[7840,-3469],[1673,-12811],[7547,-7275],[81,-5956],[-4179,-4235],[-2612,-8446],[7038,-8951]],[[654692,188814],[-2377,-5944],[5169,-5995],[-2345,-5436],[-10141,-8973],[-6596,-17291]],[[638402,145175],[-9650,-13023],[-6072,436],[-11469,13296],[-3547,928],[-8907,8705],[-1722,6792],[4564,27383],[-2629,8340]],[[598970,198032],[7481,11499],[1071,5686],[-3595,1878],[3971,12135],[3951,6045]],[[611849,235275],[1410,3268],[12854,3191],[11191,-1777]],[[822686,152366],[-3092,-10872],[-6295,-8303],[-15349,-5654],[-5913,-6491],[-13214,-951],[-9721,-7083],[-7524,-8343],[-16121,3773],[-4204,-6499]],[[741253,101943],[-16118,4968],[-7695,7039],[-2742,-2581],[-12417,-1855],[-10010,-8772],[-8541,-1697],[-9994,-5030],[-20979,-4554]],[[652757,89461],[3990,14409],[654,11812],[-4726,12793],[-9383,8219],[-4890,8481]],[[654692,188814],[8404,6465],[10897,-5906],[10502,7581],[7169,-7492],[5891,548],[6350,-3822],[10634,626],[7760,-4732],[30699,301],[10798,2794],[14733,-4034],[10288,-5022],[8225,-10123],[9645,-6001],[15999,-7631]],[[598970,198032],[-32568,-2804],[-5055,-2872],[-3990,-7307]],[[532499,170221],[2608,10089],[-1131,8292],[2169,10978],[-6209,3649],[-6727,14034],[2958,7621],[-3596,5563],[2415,13365],[886,17682],[-2055,22907],[4153,8932],[-1755,8896],[-4759,9184],[-541,15587],[2737,6838],[5285,-5207],[2760,4783],[2475,16499],[4186,17536],[-2612,8449]],[[535746,375898],[6454,2356],[6294,11442]],[[548494,389696],[3858,-27710],[6432,-12772],[-147,-8940],[4923,-9988],[5776,-16259],[5760,-11755],[1459,-14576],[5120,-8005],[4071,1172],[3361,-5883],[382,-16173],[10399,-6777],[7316,-12990],[4645,-3765]],[[652757,89461],[-11131,-2418],[-16896,-8693],[-7553,-9375],[-2644,-7509],[-12721,-13839],[-6842,-15012],[-6667,-8050],[-2655,-6844],[-5098,-2861]],[[735753,252846],[8732,-5191],[8022,2480],[5661,-3060],[28896,-1241],[10716,5118],[7153,189],[5924,-7833]],[[810857,243308],[-3597,-6714],[4176,-10766],[6513,-3280],[5984,-10448],[-1502,-23498],[6949,-3810],[2428,-10135],[-1082,-5927],[-5350,-6957],[-2690,-9407]],[[637304,239957],[8907,7810],[7202,-2011],[3252,4682],[7136,-235],[4793,4112],[4054,8403]],[[672648,262718],[5956,-6291],[11367,-201],[8715,-2828],[5269,1017],[10617,-5218],[3836,4224],[7235,-3353],[2037,-10022],[8351,4447],[-3049,4403],[2771,3950]],[[810857,243308],[13093,-2609],[3742,7068],[1056,9698],[4753,10990],[1727,14745],[-1049,27945],[4918,9866],[-8486,10705],[3497,11575],[-5842,2275],[-9387,9537],[3694,12067],[900,10224]],[[823473,377394],[1428,3431],[8584,3619],[6972,-2380],[2574,7210]],[[843031,389274],[5470,-2135],[6700,-25422],[7924,-6023],[9409,-3496],[8765,-6659],[14066,-4571],[7257,894],[-1208,5766],[2377,13765],[2808,1007],[12011,-10158],[3869,8816],[5465,2380],[5432,6471],[11081,6089],[5695,7520],[5672,-313],[4263,4660],[11475,-2905],[14705,-7666],[8520,-10560],[2327,-15822],[-1395,-12338],[-3724,133],[4561,-11307],[3443,-518],[-3719,-9705],[-859,-19022],[-1979,-9783],[-2084,-26431],[-5929,-8911],[-5369,52],[-37530,-7805],[-10602,-10645],[-5825,-10004],[-2728,12115],[13029,6582],[4922,11085],[-5111,10470],[783,-7522],[-4596,-1715],[-1712,7179],[843,17104],[4939,2665],[311,5041],[-5982,5306],[-7650,1329],[-10937,-14623],[-621,-11201],[9399,-14033],[-2850,-9290],[2187,-3994],[-7057,-1866],[-9577,-10883],[-508,-12327],[6506,502],[7021,9687],[-1506,4417],[7376,-3414],[2124,-5561],[-6702,1469],[-7401,-10320],[-8459,-7259],[1445,-3088],[-5834,-4029],[4389,-3362],[-3022,-14305],[1361,-4513],[2098,9106],[8176,13039],[5714,3571],[-6945,-19566],[-4999,-5579],[-9535,-18784],[-1420,-7550],[-5524,-3800],[-1043,-13884],[3615,-14069],[-3632,-9686],[4269,-32685],[-6540,-27856],[-2633,-15924],[-645,-12881],[-15207,-1312],[-22558,5788],[-21830,14715],[-3575,4174],[-4775,24878],[-2515,6258],[-5878,-1017],[-7312,-6101],[-6941,-2524],[-6917,16245],[-8646,-1642],[-20164,-256],[-4459,8211],[-5955,4192],[-3456,10608]],[[265678,580300],[-6939,-7259],[-5218,-14877],[-4186,-4435],[-10439,1714],[-7235,-9234],[-426,-13387],[-2360,-9275],[1312,-9949],[-6842,-16319]],[[223345,497279],[-3464,-6001],[-9858,-6347],[-10323,2681],[-7666,10258],[-6072,1296],[-4884,5095],[-4596,-972],[-2449,-9117],[-7005,1083],[-229,-7403],[-8826,9382],[-7021,-10359],[-3253,10235],[-5858,9286],[-5120,692],[-4660,8950],[-6415,-558],[-1428,-6615],[-5168,-6603],[-4022,3140],[-6956,-4012],[-6105,5319],[-1181,5475],[-4348,-1977],[-1313,-7096],[-4809,714],[-1376,6571],[-17378,5754],[-6251,12672],[-16505,15738]],[[48806,544560],[4276,6867],[-579,8045],[10611,7262],[20492,-8593],[6952,9734],[3769,469],[3138,8593],[437,9619],[2852,7644],[8995,3956],[-3760,13078],[4885,15102],[2634,15118],[8437,2100],[2909,6893]],[[124854,650447],[7240,-2814],[35294,2781],[16165,-9704],[9322,-542],[8316,-6045],[6760,-18990],[11486,-10442],[7924,-4262],[2891,-7933],[20869,-4532],[9421,-112]],[[260542,587852],[5136,-7552]],[[247220,793841],[-4645,-19241],[-4497,-8269],[1366,-7408],[8808,-21911],[7760,-7146],[5875,-9983]],[[261887,719883],[-3295,-12773],[8184,-7765],[-3743,-13179],[-6578,-6672],[5579,-11614],[4595,-17699],[4613,-8136],[-541,-13509]],[[270701,628536],[-6662,1844],[-3940,-7195],[-1656,-10627],[131,-13197],[1968,-11509]],[[124854,650447],[6348,5756],[2284,8303],[-3672,4274],[3432,13470],[9400,11978],[272,10660],[5728,7128],[2011,10682],[-3674,6554],[14559,19749],[5869,15358],[-253,6460],[4078,17838],[7912,12917],[4710,1934],[2121,5995],[-1344,21431],[5136,10027],[13764,12011]],[[203535,852972],[6073,-13798],[4348,-4481],[9947,-23633],[11846,2448],[8727,-7901],[2744,-11766]],[[189433,204575],[-3171,11972],[-15738,10147],[-10426,-4582],[-10633,2246],[-3870,5676],[-2545,11253],[-3936,3397],[-15463,680],[-7334,10192],[2722,7117],[16239,3442],[1793,5989],[-2405,5497],[-11409,5286],[-5814,6804],[1048,5778],[6187,3217],[3880,16415],[3760,2592],[-1029,7220]],[[131289,324913],[5039,9171],[-245,12046],[2574,6324],[-1297,9352],[-6512,9269],[-1066,5313],[1623,12706],[7350,7922],[3891,13526],[8174,3312],[14978,-7766],[11240,6213],[4104,-9587],[7597,-615],[966,12695],[8351,1630],[5332,6000],[10339,-3821],[3613,9464],[3901,3973],[11666,3190]],[[232907,435230],[4022,-11106],[5711,-3073],[12257,-16672],[2656,-5984],[2070,-17196],[-2398,-8447],[3333,-11164],[-3988,-17698]],[[223345,497279],[3607,-5449],[2480,-13396],[3902,-5527],[5613,-13647],[4086,-2756],[-6349,-9122],[-3777,-12152]],[[131289,324913],[-8339,10155],[-21092,10000],[-7049,12493],[-5060,-3375],[-11639,9666],[-12525,18582],[-4974,9542],[-5847,6592],[4176,8035],[-4841,16236],[2698,14290],[612,17488],[-2175,3072],[-5475,-7229],[-6109,9508],[-2744,12102],[-6087,11766],[-9562,5408],[-15126,17319],[-3487,13140],[-6644,11789],[4273,7721],[17016,671],[2580,5889],[8503,-3889],[6197,-5765],[8032,3284],[2205,5157]],[[760148,848166],[-5838,-3785],[-7301,513],[-7940,-14358],[-14754,5889],[-2246,-4312],[2197,-9544],[-5432,-4278],[-8859,9129],[-17720,83],[-4825,3368],[-9012,-14269]],[[678418,816602],[-4360,877],[-5252,8074],[-573,13039],[-3743,18527],[-11701,19989],[-14042,25896],[-14985,15140],[-2344,4588],[-1785,13141]],[[619633,935873],[7457,3218],[3356,9564],[5344,7558],[3344,11325],[1749,18885],[30022,8067],[8284,5374],[8278,-4028],[6437,582],[9809,-10660],[4280,-900],[6289,-8269],[-3278,-5017],[8611,-4570],[-1454,-4424],[2634,-9453],[5301,-5308],[6393,-12912],[-962,-11257],[5465,-6966],[0,-8991],[4340,-4289],[-3618,-3097],[7224,-13285],[-1639,-8079],[3387,-10469],[6886,-12594],[6576,-7712]],[[270701,628536],[3197,-4044],[14901,-526],[3885,-2323],[6301,-14862],[7830,7698],[10963,-1669],[5840,6436],[10629,2844],[14427,-10883],[7677,-313],[1837,-3509],[-1263,-9682],[5415,-3012],[493,6157],[21317,5050],[8710,-3363],[3956,2815]],[[396816,605350],[6726,-6362],[-3442,-11079],[4311,-6117],[8044,-6024],[1902,-10084],[3230,-4771]],[[417587,560913],[0,-18286],[-16011,-22443],[-3661,-11631],[-6858,5799],[-9318,-5633],[1509,-9665],[-4892,-8481],[-12715,302],[475,-7128],[6170,-6996],[-6433,-13945],[-4938,-972],[-4909,-20034],[2378,-16291],[-1951,-13655],[4218,-16034],[-2890,-6207]],[[357761,389613],[-4426,-1000]],[[353335,388613],[-1104,12279],[-9350,12928],[-6595,5633],[-2399,6492],[431,8787],[-2580,5783],[-1736,15365],[-5023,25610],[-5465,11346],[-4103,15214],[-5776,3524],[-10203,19158],[2165,7426],[-4366,12463],[-9186,4934],[-3431,15711],[-3182,5457],[-9650,-1429],[-6104,5006]],[[498418,850253],[9502,-11376],[4694,-12587],[-5629,-8917],[1280,-6548],[-4793,-4490],[5644,-16247],[-2988,-10046],[5005,-6325],[-1410,-12011],[575,-15096]],[[510298,746610],[-17935,-7788],[-8777,-9765],[-9716,-28467],[-9239,5336],[-7990,-8424],[-5317,-13566],[-1376,-8547],[-12093,-5834],[-11011,2213],[-8728,5989]],[[418116,677757],[2952,9375],[1474,15431],[-8234,12045],[-2656,10404],[999,11385],[-1922,5749],[-8908,8514],[-6021,2308],[-3710,7649],[-1525,16861],[6546,10867],[984,6190]],[[398095,794535],[10535,18659],[1460,8789],[10993,4682],[7547,13951],[9208,5273],[19837,-6474],[19906,938],[11799,10017],[9038,-117]],[[418116,677757],[-3218,-513],[-6039,-14192],[1803,-9665],[-1606,-7420],[-6939,-4278],[-2366,-10068],[1021,-7933],[-6464,-9895],[2508,-8443]],[[261887,719883],[13868,-984],[4083,-2637],[4791,-13117],[8072,-4940],[9321,-1542],[11274,1318],[3885,12644],[3743,-7113],[8291,-1603],[-1482,13593],[5022,392],[2121,5061],[8037,4357],[-3053,10426],[5579,16046],[8601,5508],[3279,-737],[4234,8828],[15852,8133],[1756,15878],[-1641,3391]],[[377520,792785],[3017,3616],[17558,-1866]],[[353335,388613],[1655,-14140],[-1492,-6342]],[[496953,879069],[3847,-11457],[4557,-6559],[-638,-7733],[-6301,-3067]],[[377520,792785],[-5382,-2519],[-13591,13532],[-16239,-1040],[-24809,11633],[-11078,112],[-5299,-2738]],[[301122,811765],[-9733,2587],[-3132,6106],[6563,7575],[2854,10080],[6235,10883],[2824,112],[7793,-9007],[5366,593],[5891,10201],[3940,17856],[-3612,4615],[-7187,2759],[-2037,4392],[3414,5832],[7515,-66],[7567,-3532],[6843,2258],[14962,15821],[989,4733],[-8519,11012],[-5023,9777],[-1743,8649]],[[342892,935001],[3066,5351],[5158,1465],[15574,-4469],[7355,525],[10208,-11477],[10645,6023],[12426,-5269],[3847,-5055],[10558,-3788],[7071,4921],[5213,235],[8600,6845],[14078,-2593],[9268,-9800],[1288,-8939],[5432,-6044],[8548,-4637],[8896,-18537],[6830,-689]],[[524690,740872],[705,-8240],[4870,-9510],[1414,-19095],[-1687,-14638],[3655,-17263],[-1819,-21861],[-9897,-15941],[-8972,-7664],[-6236,-9140],[-1791,-12543],[-8235,-7067],[2884,-9527],[-9350,-7397],[-229,-4464],[8350,-14470],[10666,-4134],[13913,-18782]],[[522931,539136],[-14995,-2331],[-5366,-4576],[-1443,-10358]],[[501127,521871],[-9240,8068],[-18311,-4413],[-3317,4268],[-1721,10380],[-1131,20269],[1540,4482],[-9732,357],[-7595,-5051],[-7400,693],[-7136,-2587],[-7781,3772],[-11716,-1196]],[[510298,746610],[14392,-5738]],[[247220,793841],[4530,5040],[13863,9347],[4989,1045],[11634,-4480],[5563,-6058],[9153,-6050],[5711,8515],[-1541,10565]],[[203535,852972],[3865,15443],[6086,10717],[6384,4330],[9015,1559],[1727,8535],[3246,1045],[11487,-6524],[7901,3100],[5706,8464],[5727,3090],[743,7839],[8797,8911],[4393,9576],[4044,2691],[2481,10047],[8569,-4527],[4524,4917],[5869,18180],[4557,945],[7367,-3498],[13607,-18721],[13262,-4090]],[[443598,259467],[7841,13854],[-2427,8168],[1870,19444],[3251,20391],[-842,8296],[-3836,11678],[-131,19335],[2360,9387],[-2163,13570],[4826,22867],[-1295,6916]],[[453052,413373],[19229,7990]],[[472281,421363],[6645,895],[7071,-8604],[5677,3127],[9667,526],[11766,-2246],[13289,-14324],[5825,-18795],[3525,-6044]],[[501127,521871],[-8535,-11771],[-5875,-4532],[-459,-8933],[-3262,498],[-9387,-7726],[2049,-21718],[-7595,-4200],[-2033,-5850],[3310,-9989],[2941,-26287]],[[453052,413373],[-21728,263],[-16163,-5619],[-10635,-8790],[-11387,3420],[-17623,-905],[-15552,-12436],[-2203,307]],[[551106,531011],[558,-7172],[4874,-6482],[5170,637],[-78,-38040],[1406,-6208],[10753,-12113],[208,-7218],[10323,2950],[3507,-4949],[9832,-5319],[5791,-7207],[3264,-8515],[7173,-6704],[5526,-10739]],[[619413,413932],[-5760,-17761]],[[613653,396171],[-10596,6040],[-4546,-2073],[-4236,-12766],[-4196,850],[-3447,6022],[-4252,-1609],[-12946,4074],[-17869,-4576],[-3071,-2437]],[[522931,539136],[11471,5071],[3563,-490],[10256,-8091],[2885,-4615]],[[635397,540615],[7765,6285],[7940,-7530],[212,-10851],[4072,-4229],[4671,-11575]],[[660057,512715],[-6759,-15309],[-1704,-7122],[-2574,-24774]],[[649020,465510],[1540,-11485],[-7021,-28482],[-4645,-3297],[-5300,4911],[-4827,-11035],[-9354,-2190]],[[551106,531011],[4547,12872],[11355,18539],[7744,8647],[7743,-7999],[4709,-16985],[10848,-12916],[9864,-1067],[27481,8513]],[[574029,736867],[6957,-4091],[5793,-15760],[7825,-11515],[98,-6301],[-5311,-5302],[1230,-35801],[6431,-12721],[2754,167],[1279,10011],[8634,-3004]],[[609719,652550],[343,-16079],[6121,-23007],[-3956,-4091],[-1442,-8960],[2097,-5090],[9930,-2732],[3104,-3799],[-262,-13090],[9267,3027],[4826,-1480],[-1361,-20152],[-2989,-16482]],[[524690,740872],[8236,-1313],[3087,11376],[10054,2569],[18690,-18928],[9272,2291]],[[833246,690241],[-10903,-5053],[-6743,-381],[-14213,7956],[1743,7901],[-2515,6033],[-4136,-7531],[-6908,11626],[-8889,7901],[-460,-13906],[4852,-1285],[-4064,-5386],[-7334,2090],[-3071,-6073],[-5759,-2046],[-6499,2666],[-9944,-1961],[-12209,1190]],[[736194,693982],[-6398,16124],[1999,6368],[8061,6078],[-9666,18025],[-5498,-1408],[-6054,-8023],[-6875,1844],[-4874,-7454],[-5843,1252],[-8971,8827],[-7089,4325],[-7633,915],[-4836,17303],[-5400,11012],[-7321,10011]],[[659796,779181],[8108,2593],[1443,4357],[-6481,8358],[1034,6281],[11093,-1844],[3180,1732],[1825,12928],[-1580,3016]],[[760148,848166],[4419,-17484],[9518,-5068],[2099,-3820],[-2165,-7382],[1040,-8939],[2918,-3128],[3911,-11687],[9082,-5052],[6925,-17090],[1929,-12899],[13945,-18068],[33,-3119],[9443,-2954],[7852,-21158],[2149,-20077]],[[736194,693982],[2973,-15912],[-787,-9330]],[[738380,668740],[-4168,-2950],[-12701,4805],[-10026,-1677],[-4203,11052],[-4459,3375],[-3956,-16505],[-5169,-4134],[-7351,5693],[-11584,-9794],[-4448,-6262],[-13470,-185],[-4940,-6715],[-10209,-430],[-3786,13435],[-4710,766],[-6514,-6721],[-6185,-1675],[-6913,3284],[-3869,-1552]],[[574029,736867],[2641,14079],[10452,13748],[2575,8220],[-5065,9496],[2393,2035],[8912,-9661],[10956,5235],[6088,-2614],[7487,1877],[11896,-77],[13765,8535],[8421,-949],[5246,-7610]],[[613653,396171],[13541,-20698],[4185,-14699],[-523,-7615],[5655,-14080],[7601,-1150],[4744,-6281],[3933,3151],[-15,-7988],[5628,-9487],[2148,-20079],[5611,-3319],[3743,-6916],[-3235,-13220],[5979,-11072]],[[496953,879069],[14547,5918],[4437,5921],[10262,23388],[4525,4347],[51895,7787],[17510,7257],[19504,2186]],[[738380,668740],[11668,-19045],[196,-15113],[11006,-27186],[3939,-13331],[3595,-23442],[723,-27342]],[[769507,543281],[-7907,1910],[-5318,-3854],[-4498,3922],[-12600,-1900],[-14098,-18080],[-8580,2973],[-3923,-6749],[-22679,4123],[-13174,-3246],[-1262,-10034],[-3186,-2229],[-12225,2598]],[[735753,252846],[294,11581],[-2672,9845],[6333,4246],[3394,21845],[-5579,4061],[-1295,10565],[-4333,5509],[-2182,12001],[-6857,-6113],[-1542,9057],[10897,7905],[14552,-760],[524,11173],[8192,4828],[3836,16884]],[[759315,375473],[6317,15296],[10241,7799]],[[775873,398568],[6055,-3854],[6907,324],[6612,-9487],[5825,-4492],[10682,-626],[11519,-3039]],[[649020,465510],[4671,-6436],[11373,-26549],[3890,-5542],[10618,-771],[9038,-12513],[8103,-7554],[6667,-2102],[1328,5744],[7267,-2576],[3220,-11135],[6086,-6732],[7827,3704],[983,-8100],[5662,4559],[7977,-3587],[3328,-8285],[12257,-2162]],[[831682,528900],[-2295,-20660],[4109,-17767],[644,-10167],[-1879,-9945],[4405,-13745],[1376,-27968],[-4983,-1027],[-6208,-7375],[8334,-7218],[2638,-14191],[5208,-9563]],[[775873,398568],[-3858,6917],[-3115,18449],[-6023,13151],[-7650,10156],[-13290,48462],[197,15084],[9307,13096],[8415,1961],[5022,6867],[6039,602]],[[770917,533313],[4923,-10838],[2295,-11620],[3333,-2644],[1247,13387],[-3104,9765],[1694,4336],[18131,-3157],[3475,-6738],[8716,9320],[16131,-7700],[3924,1476]],[[833246,690241],[5872,-18081],[-4,-4067],[5923,-16739],[1377,-11950],[-2295,-8130],[-678,-14235],[2831,-6101],[26,-10302],[-6146,-18179],[-1071,-12269],[-4504,-3833],[-2775,-7609],[3781,-11006],[-3901,-18840]],[[770917,533313],[-1410,9968]]]}
