{"type":"Topology","transform":{"scale":[1.9555683605624055e-7,3.972171944720933e-7],"translate":[-61.078521287999905,13.714667059000064]},"objects":{"provinces":{"type":"GeometryCollection","geometries":[{"type":"Polygon","arcs":[[0]],"properties":{"adm1_code":"LCA+00?","iso_a2":"LC","name":"LCA-00 (Saint Lucia aggregation)"}}]},"countries":{"type":"GeometryCollection","geometries":[{"type":"Polygon","arcs":[[0]],"properties":{"name":"Saint Lucia","postal":"LC","iso_a2":"LC"}}]}},"arcs":[[[0,415692],[97377,129482],[571993,430650],[171244,8604],[-22887,-43434],[131086,-59823],[50769,-277608],[-61589,-194016],[14773,-111146],[-77196,-140647],[-101330,-18644],[-69913,-120364],[-549105,113809],[-153142,98134],[35581,114526],[-37661,70477]]]}
